Workbook
Name D: WACC!$D$15
Name D_perc: WACC!$D$17
Name E: WACC!$D$14
Name E_perc: WACC!$D$16
Name kd: WACC!$D$19
Name ke: WACC!$D$12
Name scen: '52 week share price'!#REF!
Name scen: Comps!#REF!
Name scen: 'DCF model'!$E$16
Name Tax_shield: WACC!$D$18
Name Tax_shielf: WACC!$D$18
Name Tgr: '52 week share price'!#REF!
Name Tgr: Comps!#REF!
Name Tgr: 'DCF model'!$E$18
Name wacc: '52 week share price'!#REF!
Name wacc: Comps!#REF!
Name wacc: 'DCF model'!$E$17

Sheet Agenda
C3: Agenda
B6: 1 | C6: DCF | E6: X
B7: 2 | C7: Comps analysis | E7: X
B8: 3 | C8: Historical share price | E8: X
B9: 3 | C9: Football chart | E9: X

Sheet Summary
C3: Summary
A6: • | C6: Valuation
C8: Metrics | D8: DCF | E8: EV / Revenue | F8: EV / EBITDA | G8: P / Sales | H8: P / E | I8: 52-wk Range
C9: Mean | D9: 319 | E9: =Comps!R32 -> 32.283934 | F9: =Comps!S32 -> 308.2308 | G9: =Comps!T32 -> 83.687265 | H9: =Comps!U32 -> 556.36082 | I9: ='52 week share price'!G9 -> 304.5654
C10: Median | E10: =Comps!R33 -> 47.404106 | F10: =Comps!S33 -> 314.6232 | G10: =Comps!T33 -> 101.51726 | H10: =Comps!U33 -> 481.37529 | I10: ='52 week share price'!G10 -> 305.54 | K10: =AVERAGE(D11:D12,F11:F12,H11:I12) -> 350.91135
C11: 25th percentile | D11: 209 | E11: =Comps!R34 -> -23.458141 | F11: =Comps!S34 -> 226.17726 | G11: =Comps!T34 -> 27.888804 | H11: =Comps!U34 -> 403.00182 | I11: ='52 week share price'!G11 -> 299.455
C12: 75th percentile | D12: 443 | E12: =Comps!R35 -> 80.893225 | F12: =Comps!S35 -> 424.20604 | G12: =Comps!T35 -> 111.50936 | H12: =Comps!U35 -> 491.05315 | I12: ='52 week share price'!G12 -> 311.3975
A14: • | C14: Football chart
C16: Method | D16: Min | E16: Difference | F16: Max
C17: {=TRANSPOSE(D8:I8)} -> DCF | D17: =D11 -> 209 | E17: =F17-D17 -> 234 | F17: =D12 -> 443
C18: EV / Revenue | D18: =E11 -> -23.458141 | E18: =F18-D18 -> 104.35137 | F18: =E12 -> 80.893225
C19: EV / EBITDA | D19: =F11 -> 226.17726 | E19: =F19-D19 -> 198.02878 | F19: =F12 -> 424.20604
C20: P / Sales | D20: =G11 -> 27.888804 | E20: =F20-D20 -> 83.620555 | F20: =G12 -> 111.50936
C21: P / E | D21: =H11 -> 403.00182 | E21: =F21-D21 -> 88.051327 | F21: =H12 -> 491.05315
C22: 52-wk Range | D22: =I11 -> 299.455 | E22: =F22-D22 -> 11.9425 | F22: =I12 -> 311.3975
A24: • | C24: End

Sheet Comps
C3: Comps
A6: • | C6: Comps
C7: all values in B USD
C9: Name | D9: Employees | E9: Revenue | F9: Rev growth | G9: EBITDA | H9: EBITDA % | I9: Net Income | J9: NI % | K9: Price / share | L9: Market Cap | M9: EV | N9: EV / Revenue | O9: EV / EBITDA | P9: P / Sales | Q9: P / E | R9: Selected?
C10: McDonald's | D10: 150000 | E10: 26.27 | F10: 0.0125 | G10: 14.33 | H10: =G10/E10 -> 0.54548915 | I10: 8.41 | J10: =I10/E10 -> 0.32013704 | K10: 302.11 | L10: 216.86 | M10: 270.85
C11: Tyson Foods | D11: 133000 | E11: 54.44 | F11: 0.0212 | G11: 2.51 | H11: =G11/E11 -> 0.046105805 | I11: 0.474 | J11: =I11/E11 -> 0.0087068332 | K11: 56.93 | L11: 19.32 | M11: 26.97 | N11: =M11/E11 -> 0.49540779 | O11: =M11/G11 -> 10.74502 | P11: =L11/E11 -> 0.35488611 | Q11: =L11/I11 -> 40.759494 | R11: X
C12: Starbucks | D12: 381000 | E12: 37.18 | F12: 0.0279 | G12: 4.71 | H12: =G12/E12 -> 0.12668101 | I12: 1.86 | J12: =I12/E12 -> 0.050026896 | K12: 89.15 | L12: 96.16 | M12: 119.55 | N12: =M12/E12 -> 3.2154384 | O12: =M12/G12 -> 25.382166 | P12: =L12/E12 -> 2.5863367 | Q12: =L12/I12 -> 51.698925
C13: Chipotle | D13: 130000 | E13: 11.79 | F13: 0.0731 | G13: 2.28 | H13: =G13/E13 -> 0.19338422 | I13: 1.54 | J13: =I13/E13 -> 0.13061917 | K13: 38.91 | L13: 52.55 | M13: 55.78 | N13: =M13/E13 -> 4.7311281 | O13: =M13/G13 -> 24.464912 | P13: =L13/E13 -> 4.4571671 | Q13: =L13/I13 -> 34.123377 | R13: X
C14: Burger King | D14: 6000
C15: KFC | E15: 33.36
C16: Domino's Pizza | D16: 10700 | E16: 4.85 | F16: 0.0392 | G16: 1.03 | H16: =G16/E16 -> 0.21237113 | I16: 0.5 | J16: =I16/E16 -> 0.10309278 | K16: 412.22 | L16: 14.66 | M16: 19.59 | N16: =M16/E16 -> 4.0391753 | O16: =M16/G16 -> 19.019417 | P16: =L16/E16 -> 3.0226804 | Q16: =L16/I16 -> 29.32 | R16: X
C17: Jack In The Box | D17: 5046 | E17: 1.47 | F17: -0.0675 | G17: 0.034 | H17: =G17/E17 -> 0.023129252 | I17: -0.08 | J17: =I17/E17 -> -0.054421769 | K17: 20.42 | L17: 0.373 | M17: 3.47
C18: Papa John's | D18: 11400 | E18: 2.09 | F18: -0.0064 | G18: 0.173 | H18: =G18/E18 -> 0.08277512 | I18: 0.038 | J18: =I18/E18 -> 0.018181818 | K18: 39.95 | L18: 1.58 | M18: 2.53 | N18: =M18/E18 -> 1.2105263 | O18: =M18/G18 -> 14.624277 | P18: =L18/E18 -> 0.75598086 | Q18: =L18/I18 -> 41.578947 | R18: X
C19: Subway
C20: Wendy's | D20: 14500 | E20: 2.21 | F20: -0.0021 | G20: 0.552 | H20: =G20/E20 -> 0.24977376 | I20: 0.186 | J20: =I20/E20 -> 0.084162896 | K20: 8.35 | L20: 1.75 | M20: 5.55 | N20: =M20/E20 -> 2.5113122 | O20: =M20/G20 -> 10.054348 | P20: =L20/E20 -> 0.7918552 | Q20: =L20/I20 -> 9.4086022
C21: Chick-fil-A
C22: Shake Shack | D22: 12826 | E22: 1.37 | F22: 0.1349 | G22: 0.174 | H22: =G22/E22 -> 0.1270073 | I22: 0.042 | J22: =I22/E22 -> 0.030656934 | K22: 89.6 | L22: 3.77 | M22: 4.29 | N22: =M22/E22 -> 3.1313869 | O22: =M22/G22 -> 24.655172 | P22: =L22/E22 -> 2.7518248 | Q22: =L22/I22 -> 89.761905 | R22: X
C23: Mean | D23: {=AVERAGE(IF($R$11:$R$22="X",D11:D22))} -> 59585.2 | E23: {=AVERAGE(IF($R$11:$R$22="X",E11:E22))} -> 14.908 | F23: {=AVERAGE(IF($R$11:$R$22="X",F11:F22))} -> 0.0524 | G23: {=AVERAGE(IF($R$11:$R$22="X",G11:G22))} -> 1.2334 | H23: {=AVERAGE(IF($R$11:$R$22="X",H11:H22))} -> 0.13232872 | I23: {=AVERAGE(IF($R$11:$R$22="X",I11:I22))} -> 0.5188 | J23: {=AVERAGE(IF($R$11:$R$22="X",J11:J22))} -> 0.058251508 | K23: {=AVERAGE(IF($R$11:$R$22="X",K11:K22))} -> 127.522 | ... Q23: {=AVERAGE(IF($R$11:$R$22="X",Q11:Q22))} -> 47.108744
C24: Median | D24: {=MEDIAN(IF($R$11:$R$22="X",D11:D22))} -> 12826 | E24: {=MEDIAN(IF($R$11:$R$22="X",E11:E22))} -> 4.85 | F24: {=MEDIAN(IF($R$11:$R$22="X",F11:F22))} -> 0.0392 | G24: {=MEDIAN(IF($R$11:$R$22="X",G11:G22))} -> 1.03 | H24: {=MEDIAN(IF($R$11:$R$22="X",H11:H22))} -> 0.1270073 | I24: {=MEDIAN(IF($R$11:$R$22="X",I11:I22))} -> 0.474 | J24: {=MEDIAN(IF($R$11:$R$22="X",J11:J22))} -> 0.030656934 | K24: {=MEDIAN(IF($R$11:$R$22="X",K11:K22))} -> 56.93 | ... Q24: {=MEDIAN(IF($R$11:$R$22="X",Q11:Q22))} -> 40.759494
C25: 25th percentile | D25: {=PERCENTILE(IF($R$11:$R$22="X",D11:D22),0.25)} -> 11400 | E25: {=PERCENTILE(IF($R$11:$R$22="X",E11:E22),0.25)} -> 2.09 | F25: {=PERCENTILE(IF($R$11:$R$22="X",F11:F22),0.25)} -> 0.0212 | G25: {=PERCENTILE(IF($R$11:$R$22="X",G11:G22),0.25)} -> 0.174 | H25: {=PERCENTILE(IF($R$11:$R$22="X",H11:H22),0.25)} -> 0.08277512 | I25: {=PERCENTILE(IF($R$11:$R$22="X",I11:I22),0.25)} -> 0.042 | J25: {=PERCENTILE(IF($R$11:$R$22="X",J11:J22),0.25)} -> 0.018181818 | K25: {=PERCENTILE(IF($R$11:$R$22="X",K11:K22),0.25)} -> 39.95 | ... Q25: {=PERCENTILE(IF($R$11:$R$22="X",Q11:Q22),0.25)} -> 34.123377
C26: 75th percentile | D26: {=PERCENTILE(IF($R$11:$R$22="X",D11:D22),0.75)} -> 130000 | E26: {=PERCENTILE(IF($R$11:$R$22="X",E11:E22),0.75)} -> 11.79 | F26: {=PERCENTILE(IF($R$11:$R$22="X",F11:F22),0.75)} -> 0.0731 | G26: {=PERCENTILE(IF($R$11:$R$22="X",G11:G22),0.75)} -> 2.28 | H26: {=PERCENTILE(IF($R$11:$R$22="X",H11:H22),0.75)} -> 0.19338422 | I26: {=PERCENTILE(IF($R$11:$R$22="X",I11:I22),0.75)} -> 0.5 | J26: {=PERCENTILE(IF($R$11:$R$22="X",J11:J22),0.75)} -> 0.10309278 | K26: {=PERCENTILE(IF($R$11:$R$22="X",K11:K22),0.75)} -> 89.6 | ... Q26: {=PERCENTILE(IF($R$11:$R$22="X",Q11:Q22),0.75)} -> 41.578947
A28: • | C28: McD Valuation
N30: Equity value | R30: Price per share
C31: McDonald's | D31: Revenue | E31: EBITDA | F31: Net Income | G31: # Shares | H31: Cash | I31: Debt | J31: EV / Revenue | K31: EV / EBITDA | L31: P / Sales | M31: P / E | N31: EV / Revenue | O31: EV / EBITDA | P31: P / Sales | Q31: P / E | R31: EV / Revenue | S31: EV / EBITDA | T31: P / Sales | U31: P / E
C32: Mean | D32: =E10 -> 26.27 | E32: =G10 -> 14.33 | F32: =I10 -> 8.41 | G32: ='DCF model'!R97 -> 712.1 | H32: ='DCF model'!R94/1000 -> 1.047803 | I32: ='DCF model'!R95/1000 -> -49.552872 | J32: =N23 -> 2.7215249 | K32: =O23 -> 18.70176 | L32: =P23 -> 2.2685079 | M32: =Q23 -> 47.108744 | N32: =J32*D32+H32+I32 -> 22.989389 | O32: =K32*E32+H32+I32 -> 219.49115 | P32: =L32*D32 -> 59.593701 | Q32: =M32*F32 -> 396.18454 | R32: =N32*1000/$G32 -> 32.283934 | S32: =O32*1000/$G32 -> 308.2308 | T32: =P32*1000/$G32 -> 83.687265 | U32: =Q32*1000/$G32 -> 556.36082
C33: Median | D33: =D32 -> 26.27 | E33: =E32 -> 14.33 | F33: =F32 -> 8.41 | G33: =G32 -> 712.1 | H33: =H32 -> 1.047803 | I33: =I32 -> -49.552872 | J33: =N24 -> 3.1313869 | K33: =O24 -> 19.019417 | L33: =P24 -> 2.7518248 | M33: =Q24 -> 40.759494 | N33: =J33*D33+H33+I33 -> 33.756464 | O33: =K33*E33+H33+I33 -> 224.04318 | P33: =L33*D33 -> 72.290438 | Q33: =M33*F33 -> 342.78734 | R33: =N33*1000/$G33 -> 47.404106 | S33: =O33*1000/$G33 -> 314.6232 | T33: =P33*1000/$G33 -> 101.51726 | U33: =Q33*1000/$G33 -> 481.37529
C34: 25th percentile | D34: =D33 -> 26.27 | E34: =E33 -> 14.33 | F34: =F33 -> 8.41 | G34: =G33 -> 712.1 | H34: =H33 -> 1.047803 | I34: =I33 -> -49.552872 | J34: =N25 -> 1.2105263 | K34: =O25 -> 14.624277 | L34: =P25 -> 0.75598086 | M34: =Q25 -> 34.123377 | N34: =J34*D34+H34+I34 -> -16.704542 | O34: =K34*E34+H34+I34 -> 161.06083 | P34: =L34*D34 -> 19.859617 | Q34: =M34*F34 -> 286.9776 | R34: =N34*1000/$G34 -> -23.458141 | S34: =O34*1000/$G34 -> 226.17726 | T34: =P34*1000/$G34 -> 27.888804 | U34: =Q34*1000/$G34 -> 403.00182
C35: 75th percentile | D35: =D34 -> 26.27 | E35: =E34 -> 14.33 | F35: =F34 -> 8.41 | G35: =G34 -> 712.1 | H35: =H34 -> 1.047803 | I35: =I34 -> -49.552872 | J35: =N26 -> 4.0391753 | K35: =O26 -> 24.464912 | L35: =P26 -> 3.0226804 | M35: =Q26 -> 41.578947 | N35: =J35*D35+H35+I35 -> 57.604065 | O35: =K35*E35+H35+I35 -> 302.07712 | P35: =L35*D35 -> 79.405814 | Q35: =M35*F35 -> 349.67895 | R35: =N35*1000/$G35 -> 80.893225 | S35: =O35*1000/$G35 -> 424.20604 | T35: =P35*1000/$G35 -> 111.50936 | U35: =Q35*1000/$G35 -> 491.05315
A37: • | C37: End

Sheet 52 week share price
C3: Share price
A5: • | C5: McD Valuation
C8: {=_xlfn.STOCKHISTORY("MCD","1/1/2025","1/1/2026")} -> Date | D8: Close | F8: Valuation
C9: 45659 | D9: 292.51 | F9: Mean | G9: =AVERAGE(D9:D258) -> 304.5654
C10: 45660 | D10: 294.78 | F10: Median | G10: =MEDIAN(D9:D258) -> 305.54
C11: 45663 | D11: 292.18 | F11: 25th percentile | G11: =PERCENTILE(D9:D258,0.25) -> 299.455
C12: 45664 | D12: 289.34 | F12: 75th percentile | G12: =PERCENTILE(D9:D258,0.75) -> 311.3975
C13: 45665 | D13: 286.9
C14: 45667 | D14: 282.31
C15: 45670 | D15: 283.63
C16: 45671 | D16: 281.58
C17: 45672 | D17: 282.3
C18: 45673 | D18: 279.74
C19: 45674 | D19: 280.95
C20: 45678 | D20: 282.61
C21: 45679 | D21: 281.35
C22: 45680 | D22: 284.43
C23: 45681 | D23: 285.46
C24: 45684 | D24: 293.09
... C258: 46022 | D258: 305.63

Sheet DCF model
C3: DCF model
A6: • | C6: Overview
C8: Comp name | E8: McDonald's Corporation | G8: Valuation USD | I8: =R98*I11 -> 442.67444
C9: Ticker | E9: MCD | G9: % delta vs current | I9: =I8/E11-1 -> 0.42591218
C10: Date | E10: =TODAY() -> 46029
C11: Price per share | E11: 310.45 | G11: Exch. EUR-USD | I11: 1.18
A13: • | C13: Assumptions
C15: Triggers | G15: Conservative | H15: Year | I15: Amount | K15: Base / Street | L15: Year | M15: Amount | O15: Optimistic | P15: Year | Q15: Amount
C16: Scenario | E16: 3 | G16: Revenue gr | H16: 25-'30 | I16: -0.2 | O16: Revenue gr | P16: 25-'30 | Q16: 0.55
C17: WACC | E17: =CHOOSE(scen,M20,I20,Q20) -> 0.06 | G17: EBITDA margin | H17: 25 | I17: -0.05 | O17: EBITDA margin | P17: 25 | Q17: 0
C18: TGR | E18: =CHOOSE(scen,M21,I21,Q21) -> 0.028 | G18: EBITDA margin | H18: 30 | I18: -0.15 | O18: EBITDA margin | P18: 30 | Q18: 0.05
G19: D&A | H19: 25 | I19: 0 | O19: D&A | P19: 25-'30 | Q19: 0
G20: WACC | I20: 0.062 | K20: WACC | M20: =WACC!D21 -> 0.061305018 | O20: WACC | Q20: 0.06
G21: TGR | I21: 0.022 | K21: TGR | M21: 0.025 | O21: TGR | Q21: 0.028
A23: • | C23: Income statement
H25: Actuals | M25: Projections
C26: €M | H26: 2020 | I26: =+H26+1 -> 2021 | J26: =+I26+1 -> 2022 | K26: =+J26+1 -> 2023 | L26: =+K26+1 -> 2024 | M26: =+L26+1 -> 2025 | N26: =+M26+1 -> 2026 | O26: =+N26+1 -> 2027 | P26: =+O26+1 -> 2028 | ... R26: =+Q26+1 -> 2030
C27: Revenue | H27: =IS!H11 -> 16849 | I27: =IS!I11 -> 19647 | J27: =IS!J11 -> 22058 | K27: =IS!K11 -> 23581 | L27: =IS!L11 -> 23962 | M27: =L27*(1+M28) -> 24890.528 | N27: =M27*(1+N28) -> 25855.035 | O27: =N27*(1+O28) -> 26856.918 | P27: =O27*(1+P28) -> 27897.624 | Q27: =P27*(1+Q28) -> 28978.657 | R27: =Q27*(1+R28) -> 30101.579
C28: % growth | I28: =I27/H27-1 -> 0.16606327 | J28: =J27/I27-1 -> 0.12271594 | K28: =K27/J27-1 -> 0.069045244 | L28: =L27/K27-1 -> 0.016157076 | M28: =OFFSET(M28,scen,0) -> 0.03875 | N28: =OFFSET(N28,scen,0) -> 0.03875 | O28: =OFFSET(O28,scen,0) -> 0.03875 | P28: =OFFSET(P28,scen,0) -> 0.03875 | Q28: =OFFSET(Q28,scen,0) -> 0.03875 | R28: =OFFSET(R28,scen,0) -> 0.03875
C29: 1. Base | M29: 0.025 | N29: =M29 -> 0.025 | O29: =N29 -> 0.025 | P29: =O29 -> 0.025 | Q29: =P29 -> 0.025 | R29: =Q29 -> 0.025
C30: 2. Conservative | M30: =M29*(1+I16) -> 0.02 | N30: =M30 -> 0.02 | O30: =N30 -> 0.02 | P30: =O30 -> 0.02 | Q30: =P30 -> 0.02 | R30: =Q30 -> 0.02
C31: 3. Optimistic | M31: =M29*(1+Q16) -> 0.03875 | N31: =M31 -> 0.03875 | O31: =N31 -> 0.03875 | P31: =O31 -> 0.03875 | Q31: =P31 -> 0.03875 | R31: =Q31 -> 0.03875
C33: COGS | H33: =IS!H13*-1 -> -6788 | I33: =IS!I13*-1 -> -7482 | J33: =IS!J13*-1 -> -7831 | K33: =IS!K13*-1 -> -8419 | L33: =IS!L13*-1 -> -8525 | M33: =M35-M27 -> -8374.2882 | N33: =N35-N27 -> -8184.1046 | O33: =O35-O27 -> -7950.5683 | P33: =P35-P27 -> -7669.4837 | Q33: =Q35-Q27 -> -7336.3167 | R33: =R35-R27 -> -6946.1696
C35: Gross profit | H35: =H27+H33 -> 10061 | I35: =I27+I33 -> 12165 | J35: =J27+J33 -> 14227 | K35: =K27+K33 -> 15162 | L35: =L27+L33 -> 15437 | M35: =M27*M36 -> 16516.239 | N35: =N27*N36 -> 17670.931 | O35: =O27*O36 -> 18906.35 | P35: =P27*P36 -> 20228.14 | Q35: =Q27*Q36 -> 21642.34 | R35: =R27*R36 -> 23155.41
C36: % margin | H36: =H35/H$27 -> 0.59712743 | I36: =I35/I$27 -> 0.6191785 | J36: =J35/J$27 -> 0.64498141 | K36: =K35/K$27 -> 0.64297528 | L36: =L35/L$27 -> 0.64422836 | M36: =L36*(1+M37) -> 0.66355521 | N36: =M36*(1+N37) -> 0.68346187 | O36: =N36*(1+O37) -> 0.70396572 | P36: =O36*(1+P37) -> 0.7250847 | Q36: =P36*(1+Q37) -> 0.74683724 | R36: =Q36*(1+R37) -> 0.76924235
C37: % growth | I37: =I36/H36-1 -> 0.036928591 | J37: =J36/I36-1 -> 0.041672817 | K37: =K36/J36-1 -> -0.0031103779 | L37: =L36/K36-1 -> 0.001948885 | M37: =OFFSET(M37,scen,0) -> 0.03 | N37: =OFFSET(N37,scen,0) -> 0.03 | O37: =OFFSET(O37,scen,0) -> 0.03 | P37: =OFFSET(P37,scen,0) -> 0.03 | Q37: =OFFSET(Q37,scen,0) -> 0.03 | R37: =OFFSET(R37,scen,0) -> 0.03
C38: 1. Base | M38: =AVERAGE(J37:L37) -> 0.013503775 | N38: 0.012 | O38: 0.01 | P38: =O38 -> 0.01 | Q38: =P38 -> 0.01 | R38: =Q38 -> 0.01
C39: 2. Conservative | M39: =AVERAGE(K37:L37) -> -0.00058074646 | N39: =M39 -> -0.00058074646 | O39: =N39 -> -0.00058074646 | P39: 0 | Q39: 0 | R39: 0
C40: 3. Optimistic | M40: 0.03 | N40: =M40 -> 0.03 | O40: =N40 -> 0.03 | P40: =O40 -> 0.03 | Q40: =P40 -> 0.03 | R40: =Q40 -> 0.03
C42: Opex | H42: =IS!H18*-1 -> -2243 | I42: =IS!I18*-1 -> -2316 | J42: =IS!J18*-1 -> -2595 | K42: =IS!K18*-1 -> -2492 | L42: =IS!L18*-1 -> -2535 | M42: =M45-M35 -> -2863.1481 | N42: =N45-N35 -> -3162.8954 | O42: =O45-O35 -> -3497.6128 | P42: =P45-P35 -> -3870.6818 | Q42: =Q45-Q35 -> -4285.7717 | R42: =R45-R35 -> -4746.8627
C43: % sales | H43: =H42/H27*-1 -> 0.13312363 | I43: =I42/I27*-1 -> 0.11788059 | J43: =J42/J27*-1 -> 0.11764439 | K43: =K42/K27*-1 -> 0.1056783 | L43: =L42/L27*-1 -> 0.1057925 | M43: =M42/M27*-1 -> 0.11502963 | N43: =N42/N27*-1 -> 0.12233189 | O43: =O42/O27*-1 -> 0.13023135 | ... R43: =R42/R27*-1 -> 0.1576948
C45: EBITDA | H45: =H35+H42 -> 7818 | I45: =I35+I42 -> 9849 | J45: =J35+J42 -> 11632 | K45: =K35+K42 -> 12670 | L45: =L35+L42 -> 12902 | M45: =M27*M46 -> 13653.091 | N45: =N27*N46 -> 14508.035 | O45: =O27*O46 -> 15408.737 | P45: =P27*P46 -> 16357.458 | Q45: =Q27*Q46 -> 17356.568 | R45: =R27*R46 -> 18408.547
C46: % margin | H46: =H45/H$27 -> 0.4640038 | I46: =I45/I$27 -> 0.50129791 | J46: =J45/J$27 -> 0.52733702 | K46: =K45/K$27 -> 0.53729698 | L46: =L45/L$27 -> 0.53843586 | M46: =OFFSET(M46,scen,0) -> 0.54852559 | N46: =OFFSET(N46,scen,0) -> 0.56112998 | O46: =OFFSET(O46,scen,0) -> 0.57373437 | P46: =OFFSET(P46,scen,0) -> 0.58633876 | Q46: =OFFSET(Q46,scen,0) -> 0.59894316 | R46: =OFFSET(R46,scen,0) -> 0.61154755
C47: 1. Base | M47: ='Estimates IS'!H14 -> 0.54852559 | N47: ='Estimates IS'!I14 -> 0.5547934 | O47: ='Estimates IS'!J14 -> 0.56139184 | P47: ='Estimates IS'!K14 -> 0.56057839 | Q47: ='Estimates IS'!L14 -> 0.57712169 | R47: ='Estimates IS'!M14 -> 0.58242624
C48: 2. Conservative | M48: =M47*(1+I17) -> 0.52109931 | N48: =M48-(($M$48-$R$48)/($R$26-$M$26)) -> 0.51589191 | O48: =N48-(($M$48-$R$48)/($R$26-$M$26)) -> 0.5106845 | P48: =O48-(($M$48-$R$48)/($R$26-$M$26)) -> 0.5054771 | Q48: =P48-(($M$48-$R$48)/($R$26-$M$26)) -> 0.5002697 | R48: =R47*(1+I18) -> 0.4950623
C49: 3. Optimistic | M49: =M47*(1+Q17) -> 0.54852559 | N49: =M49+(($R$49-$M$49)/($R$26-$M$26)) -> 0.56112998 | O49: =N49+(($R$49-$M$49)/($R$26-$M$26)) -> 0.57373437 | P49: =O49+(($R$49-$M$49)/($R$26-$M$26)) -> 0.58633876 | Q49: =P49+(($R$49-$M$49)/($R$26-$M$26)) -> 0.59894316 | R49: =R47*(1+Q18) -> 0.61154755
C51: D&A | H51: =IS!H14*-1 -> -1536 | I51: =IS!I14*-1 -> -1580 | J51: =IS!J14*-1 -> -1780 | K51: =IS!K14*-1 -> -1830 | L51: =IS!L14*-1 -> -1939 | M51: =M27*M52*-1 -> -2032.4746 | N51: =N27*N52*-1 -> -2084.6724 | O51: =O27*O52*-1 -> -2189.634 | P51: =P27*P52*-1 -> -2163.4459 | Q51: =Q27*Q52*-1 -> -1924.7536 | R51: =R27*R52*-1 -> -1917.456
C52: % sales | H52: =H51/H$27*-1 -> 0.09116268 | I52: =I51/I$27*-1 -> 0.080419402 | J52: =J51/J$27*-1 -> 0.080696346 | K52: =K51/K$27*-1 -> 0.077604851 | L52: =L51/L$27*-1 -> 0.08091979 | M52: =OFFSET(M52,scen,0) -> 0.081656548 | N52: =OFFSET(N52,scen,0) -> 0.080629261 | O52: =OFFSET(O52,scen,0) -> 0.08152961 | P52: =OFFSET(P52,scen,0) -> 0.077549467 | Q52: =OFFSET(Q52,scen,0) -> 0.066419698 | R52: =OFFSET(R52,scen,0) -> 0.063699513
C53: 1. Base | M53: ='Estimates IS'!H18 -> 0.081656548 | N53: ='Estimates IS'!I18 -> 0.080629261 | O53: ='Estimates IS'!J18 -> 0.08152961 | P53: ='Estimates IS'!K18 -> 0.077549467 | Q53: ='Estimates IS'!L18 -> 0.066419698 | R53: ='Estimates IS'!M18 -> 0.063699513
C54: 2. Conservative | M54: =M53*(1+I19) -> 0.081656548 | N54: =M54 -> 0.081656548 | O54: =N54 -> 0.081656548 | P54: =O54 -> 0.081656548 | Q54: =P54 -> 0.081656548 | R54: =Q54 -> 0.081656548
C55: 3. Optimistic | M55: =M53*(1+Q19) -> 0.081656548 | N55: =N53*(1+R19) -> 0.080629261 | O55: =O53*(1+S19) -> 0.08152961 | P55: =P53*(1+T19) -> 0.077549467 | Q55: =Q53*(1+U19) -> 0.066419698 | R55: =R53*(1+V19) -> 0.063699513
C57: EBIT | H57: =H45+H51 -> 6282 | I57: =I45+I51 -> 8269 | J57: =J45+J51 -> 9852 | K57: =K45+K51 -> 10840 | L57: =L45+L51 -> 10963 | M57: =M45+M51 -> 11620.617 | N57: =N45+N51 -> 12423.363 | O57: =O45+O51 -> 13219.103 | ... R57: =R45+R51 -> 16491.091
C58: % margin | H58: =H57/H$27 -> 0.37284112 | I58: =I57/I$27 -> 0.42087851 | J58: =J57/J$27 -> 0.44664067 | K58: =K57/K$27 -> 0.45969213 | L58: =L57/L$27 -> 0.45751607 | M58: =M57/M$27 -> 0.46686904 | N58: =N57/N$27 -> 0.48050072 | O58: =O57/O$27 -> 0.49220476 | ... R58: =R57/R$27 -> 0.54784804
C60: Interests | H60: =IS!H25*-1 -> -1075 | I60: =IS!I25*-1 -> -1010 | J60: =IS!J25*-1 -> -1236 | K60: =IS!K25*-1 -> -1297 | L60: =IS!L25*-1 -> -1435 | M60: =M27*M61*-1 -> -1490.6063 | N60: =N27*N61*-1 -> -1548.3672 | O60: =O27*O61*-1 -> -1608.3665 | P60: =P27*P61*-1 -> -1670.6907 | Q60: =Q27*Q61*-1 -> -1735.4299 | R60: =R27*R61*-1 -> -1802.6778
C61: % sales | H61: =H60/H27*-1 -> 0.063802006 | I61: =I60/I27*-1 -> 0.05140734 | J61: =J60/J27*-1 -> 0.056034092 | K61: =K60/K27*-1 -> 0.055001908 | L61: =L60/L27*-1 -> 0.059886487 | M61: =L61 -> 0.059886487 | N61: =M61 -> 0.059886487 | O61: =N61 -> 0.059886487 | P61: =O61 -> 0.059886487 | Q61: =P61 -> 0.059886487 | R61: =Q61 -> 0.059886487
C63: Taxable income | H63: =H57+H60 -> 5207 | I63: =I57+I60 -> 7259 | J63: =J57+J60 -> 8616 | K63: =K57+K60 -> 9543 | L63: =L57+L60 -> 9528 | M63: =M57+M60 -> 10130.01 | N63: =N57+N60 -> 10874.996 | O63: =O57+O60 -> 11610.736 | ... R63: =R57+R60 -> 14688.413
C64: % margin | H64: =H63/H$27 -> 0.30903911 | I64: =I63/I$27 -> 0.36947117 | J64: =J63/J$27 -> 0.39060658 | K64: =K63/K$27 -> 0.40469022 | L64: =L63/L$27 -> 0.39762958 | M64: =M63/M$27 -> 0.40698255 | N64: =N63/N$27 -> 0.42061423 | O64: =O63/O$27 -> 0.43231827 | ... R64: =R63/R$27 -> 0.48796155
C66: Taxes | H66: =IS!H33*-1 -> -1237 | I66: =IS!I33*-1 -> -1339 | J66: =IS!J33*-1 -> -1568 | K66: =IS!K33*-1 -> -1899 | L66: =IS!L33*-1 -> -1961 | M66: =M63*M67*-1 -> -2043.8733 | N66: =N63*N67*-1 -> -2194.1847 | O66: =O63*O67*-1 -> -2342.6309 | P66: =P63*P67*-1 -> -2526.7579 | Q66: =Q63*Q67*-1 -> -2763.4399 | R66: =R63*R67*-1 -> -2963.5959
C67: % tax rate | H67: =H66/H63*-1 -> 0.23756482 | I67: =I66/I63*-1 -> 0.18446067 | J67: =J66/J63*-1 -> 0.181987 | K67: =K66/K63*-1 -> 0.19899403 | L67: =L66/L63*-1 -> 0.20581444 | M67: =AVERAGE(H67:L67) -> 0.20176419 | N67: =M67 -> 0.20176419 | O67: =N67 -> 0.20176419 | P67: =O67 -> 0.20176419 | Q67: =P67 -> 0.20176419 | R67: =Q67 -> 0.20176419
C69: Net income | H69: =H63+H66 -> 3970 | I69: =I63+I66 -> 5920 | J69: =J63+J66 -> 7048 | K69: =K63+K66 -> 7644 | L69: =L63+L66 -> 7567 | M69: =M63+M66 -> 8086.137 | N69: =N63+N66 -> 8680.8111 | O69: =O63+O66 -> 9268.1056 | ... R69: =R63+R66 -> 11724.818
C70: % margin | H70: =H69/H$27 -> 0.23562229 | I70: =I69/I$27 -> 0.30131827 | J70: =J69/J$27 -> 0.31952126 | K70: =K69/K$27 -> 0.32415928 | L70: =L69/L$27 -> 0.31579167 | M70: =M69/M$27 -> 0.32486805 | N70: =N69/N$27 -> 0.33574934 | O70: =O69/O$27 -> 0.34509193 | ... R70: =R69/R$27 -> 0.38950838
A72: • | C72: DCF
H74: Actuals | M74: Projections
C75: €M | H75: 2020 | I75: =+H75+1 -> 2021 | J75: =+I75+1 -> 2022 | K75: =+J75+1 -> 2023 | L75: =+K75+1 -> 2024 | M75: =+L75+1 -> 2025 | N75: =+M75+1 -> 2026 | O75: =+N75+1 -> 2027 | P75: =+O75+1 -> 2028 | ... R75: =+Q75+1 -> 2030
C76: EBIT | M76: =M57 -> 11620.617 | N76: =N57 -> 12423.363 | O76: =O57 -> 13219.103 | P76: =P57 -> 14194.012 | Q76: =Q57 -> 15431.814 | R76: =R57 -> 16491.091
C77: (1-Tax) | M77: =(1-M67) -> 0.79823581 | N77: =(1-N67) -> 0.79823581 | O77: =(1-O67) -> 0.79823581 | P77: =(1-P67) -> 0.79823581 | Q77: =(1-Q67) -> 0.79823581 | R77: =(1-R67) -> 0.79823581
C78: EBIAT (or NOPAT) | M78: =M76*M77 -> 9275.9923 | N78: =N76*N77 -> 9916.7733 | O78: =O76*O77 -> 10551.961 | P78: =P76*P77 -> 11330.169 | Q78: =Q76*Q77 -> 12318.227 | R78: =R76*R77 -> 13163.78
C79: Plus D&A | M79: =-M51 -> 2032.4746 | N79: =-N51 -> 2084.6724 | O79: =-O51 -> 2189.634 | P79: =-P51 -> 2163.4459 | Q79: =-Q51 -> 1924.7536 | R79: =-R51 -> 1917.456
C80: Less Capex | M80: =-'Estimates IS'!H25 -> -2707 | N80: =-'Estimates IS'!I25 -> -2928 | O80: =-'Estimates IS'!J25 -> -3261 | P80: =-'Estimates IS'!K25 -> -3525 | Q80: =-'Estimates IS'!L25 -> -3774.0819 | R80: =-'Estimates IS'!M25 -> -4040.7644
C81: Less Change in WC | M81: =-M151 -> -46.811319 | N81: =-N151 -> -114.5732 | O81: =-O151 -> -123.20731 | P81: =-P151 -> -132.46922 | Q81: =-Q151 -> -142.40378 | R81: =-R151 -> -153.05898
C82: Free Cash Flow | M82: =SUM(M78:M81) -> 8554.6555 | N82: =SUM(N78:N81) -> 8958.8725 | O82: =SUM(O78:O81) -> 9357.3881 | P82: =SUM(P78:P81) -> 9836.1455 | Q82: =SUM(Q78:Q81) -> 10326.495 | R82: =SUM(R78:R81) -> 10887.412
C84: Discount period not corrected | M84: 1 | N84: =M84+1 -> 2 | O84: =N84+1 -> 3 | P84: =O84+1 -> 4 | Q84: =P84+1 -> 5 | R84: =Q84+1 -> 6
C85: Fraction of year left | M85: =1-(9/12) -> 0.25 | N85: =M85+1 -> 1.25 | O85: =N85+1 -> 2.25 | P85: =O85+1 -> 3.25 | Q85: =P85+1 -> 4.25 | R85: =Q85+1 -> 5.25
C86: Mid year convention DP | M86: =M85*0.5 -> 0.125 | N86: =M85+0.5 -> 0.75 | O86: =N86+1 -> 1.75 | P86: =O86+1 -> 2.75 | Q86: =P86+1 -> 3.75 | R86: =Q86+1 -> 4.75
C88: Discounted FCF | M88: =M82/(1+wacc)^M86 -> 8492.5731 | N88: =N82/(1+wacc)^N86 -> 8575.7864 | O88: =O82/(1+wacc)^O86 -> 8450.2465 | P88: =P82/(1+wacc)^P86 -> 8379.8031 | Q88: =Q82/(1+wacc)^Q86 -> 8299.5766 | R88: =R82/(1+wacc)^R86 -> 8255.0898
C90: Terminal value | R90: =(R82*(1+Tgr))/(wacc-Tgr) -> 349758.12
C91: Discounted TV | R91: =R90/(1+wacc)^R86 -> 265194.76
C93: Enterprise value | R93: =R91+SUM(M88:R88) -> 315647.84
C94: Plus Cash | R94: =BS!L10 -> 1047.803
C95: Less Debt | R95: =-D -> -49552.872
C96: Equity value | R96: =SUM(R93:R95) -> 267142.77
C97: Number of shares | R97: =IS!M48 -> 712.1
C98: Price per share | R98: =R96/R97 -> 375.14783
A100: • | C100: Sensitivity analysis
C102: Dynamic | F102: WACC
E103: =R98 -> 375.14783 | F103: 0.06 | G103: =F103+0.25% -> 0.0625 | H103: =G103+0.25% -> 0.065 | I103: =H103+0.25% -> 0.0675 | J103: =I103+0.25% -> 0.07 | K103: =J103+0.25% -> 0.0725 | L103: =K103+0.25% -> 0.075
D104: TGR | E104: 0.02 | F104: 298.34686 | G104: 277.48103 | H104: 258.93452 | I104: 242.34112 | J104: 227.40784 | K104: 213.89751 | L104: 201.61608
E105: =E104+0.25% -> 0.0225 | F105: 318.82712 | G105: 295.39291 | H105: 274.71649 | I105: 256.33822 | J105: 239.89521 | K105: 225.09717 | L105: 211.70908
E106: =E105+0.25% -> 0.025 | F106: 342.23313 | G106: 315.69304 | H106: 292.47121 | I106: 271.98204 | J106: 253.77006 | K106: 237.47573 | L106: 222.81137
E107: =E106+0.25% -> 0.0275 | F107: 369.24006 | G107: 338.8932 | H107: 312.59322 | I107: 289.58133 | J107: 269.27725 | K107: 251.22969 | L107: 235.08232
E108: =E107+0.25% -> 0.03 | F108: 400.74815 | G108: 365.66261 | H108: 335.58981 | I108: 309.52719 | J108: 286.72284 | K108: 266.60176 | L108: 248.71672
C111: Base case | F111: WACC
E112: 270.50981 | F112: 0.06 | G112: 0.0625 | H112: 0.065 | I112: 0.0675 | J112: 0.07 | K112: 0.0725 | L112: 0.075
D113: TGR | E113: 0.02 | F113: 245.59545 | G113: 228.00046 | H113: 212.35986 | I113: 198.36507 | J113: 185.76923 | K113: 174.37247 | L113: 164.01131
E114: 0.0225 | F114: 262.85243 | G114: 243.09328 | H114: 225.65799 | I114: 210.15924 | J114: 196.29127 | K114: 183.80947 | L114: 172.51581
E115: 0.025 | F115: 282.57469 | G115: 260.19848 | H115: 240.61838 | I115: 223.34095 | J115: 207.98243 | K115: 194.23984 | L115: 181.87077
E116: 0.0275 | F116: 305.33114 | G116: 279.74728 | H116: 257.57349 | I116: 238.17039 | J116: 221.04903 | K116: 205.82913 | L116: 192.21047
E117: 0.03 | F117: 331.88034 | G117: 302.30359 | H117: 276.95076 | I117: 254.97707 | J117: 235.74894 | K117: 218.78187 | L117: 203.69901
C120: Conservative case | F120: WACC
E121: 176.75668 | F121: 0.06 | G121: 0.0625 | H121: 0.065 | I121: 0.0675 | J121: 0.07 | K121: 0.0725 | L121: 0.075
D122: TGR | E122: 0.02 | F122: 178.30692 | G122: 164.79069 | H122: 152.77418 | I122: 142.02059 | J122: 132.3405 | K122: 123.58058 | L122: 115.61537
E123: 0.0225 | F123: 191.54799 | G123: 176.37124 | H123: 162.97767 | I123: 151.07011 | J123: 140.41394 | K123: 130.82148 | L123: 122.14078
E124: 0.025 | F124: 206.68064 | G124: 189.49585 | H124: 174.4566 | I124: 161.18428 | J124: 149.38443 | K124: 138.82457 | L124: 129.31873
E125: 0.0275 | F125: 224.1414 | G125: 204.49542 | H125: 187.46606 | I125: 172.56273 | J125: 159.41027 | K125: 147.7169 | L125: 137.25225
E126: 0.03 | F126: 244.51228 | G126: 221.8026 | H126: 202.33401 | I126: 185.4583 | J126: 170.68934 | K126: 157.65538 | L126: 146.06727
C129: Optimistic case | F129: WACC
E130: 375.14783 | F130: 0.06 | G130: 0.0625 | H130: 0.065 | I130: 0.0675 | J130: 0.07 | K130: 0.0725 | L130: 0.075
D131: TGR | E131: 0.02 | F131: 298.34686 | G131: 277.48103 | H131: 258.93452 | I131: 242.34112 | J131: 227.40784 | K131: 213.89751 | L131: 201.61608
E132: 0.0225 | F132: 318.82712 | G132: 295.39291 | H132: 274.71649 | I132: 256.33822 | J132: 239.89521 | K132: 225.09717 | L132: 211.70908
E133: 0.025 | F133: 342.23313 | G133: 315.69304 | H133: 292.47121 | I133: 271.98204 | J133: 253.77006 | K133: 237.47573 | L133: 222.81137
...

Sheet INPUT>>

Sheet WACC
C3: WACC
C5: WACC = kE*(E/E+D) + kd * D/D+E * (1-tax)
C6: Ke = Rf + Beta * (Rm - Rf)
C7: Rm - Rf = MRP
C9: Rf | D9: 0.0438 | F9: 10-yr treas yield - google
C10: Beta | D10: 0.57 | F10: Factset
C11: MRP | D11: 0.046 | F11: Damodoran
C12: Ke | D12: =D9+D10*D11 -> 0.07002
C14: E | D14: 217140 | F14: Factset
C15: D | D15: =BS!L48 -> 49552.872 | F15: BS
C16: E% | D16: =E/(SUM(D14:D15)) -> 0.81419499
C17: D% | D17: =D/SUM(D14:D15) -> 0.18580501
C18: 1-Tax | D18: =(1-'DCF model'!M67) -> 0.79823581
C19: Kd | D19: =IS!L25/D -> 0.028958968
C21: WACC | D21: =ke*E_perc+kd*Tax_shield*D_perc -> 0.061305018

Sheet Estimates IS
B1: MCD-US
B2: Income Statement (M)
C3: Dec '20 | D3: Dec '21 | E3: Dec '22 | F3: Dec '23 | G3: Dec '24 | H3: Dec '25E | I3: Dec '26E | J3: Dec '27E | K3: Dec '28E | L3: Dec '29E | M3: Dec '30E
B4: Sales | C4: 15845 | D4: 20830 | E4: 21346 | F4: 23769 | G4: 25127 | H4: 23060 | I4: 24346 | J4: 25549 | K4: 26280 | L4: 26724 | M4: 27928
B5: Cost of Sales | C5: 5759 | D5: 7218 | E5: 6796 | F5: 7668 | G5: 8079 | H5: 7100 | I5: 7503 | J5: 7846 | K5: - | L5: - | M5: -
B6: Gross Income | C6: - | D6: 10463 | E6: 11493 | F6: 13578 | G6: - | H6: 12019 | I6: 12871 | J6: - | K6: - | L6: - | M6: -
B7: Compensation and Benefits | C7: - | D7: - | E7: - | F7: - | G7: - | H7: 2212 | I7: 2328 | J7: - | K7: - | L7: - | M7: -
B8: EBITDA | C8: 7314 | D8: 10722 | E8: 11281 | F8: 12964 | G8: 13602 | H8: 12649 | I8: 13507 | J8: 14343 | K8: 14732 | L8: 15423 | M8: 16266
B9: Operating Income | C9: 5890 | D9: 9158 | E9: 9558 | F9: 11114 | G9: 11634 | H9: 10766 | I9: 11544 | J9: 12260 | K9: 12694 | L9: 13648 | M9: 14487
B10: Pretax Income | C10: 4926 | D10: 7998 | E10: 8595 | F10: 9820 | G10: 10258 | H10: 9456 | I10: 10235 | J10: 10972 | K10: 11366 | L10: 12298 | M10: 13128
B11: Tax Expense | C11: 1163 | D11: 1609 | E11: 1517 | F11: 1915 | G11: 2056 | H11: 2020 | I11: 2158 | J11: 2327 | K11: 2418 | L11: 2582 | M11: 2757
B12: Net Income | C12: 3744 | D12: 6258 | E12: 6892 | F12: 8151 | G12: 8200 | H12: 7465 | I12: 8083 | J12: 8675 | K12: 8988 | L12: 9813 | M12: 10466
B14: % margin EBITDA | H14: =H8/H4 -> 0.54852559 | I14: =I8/I4 -> 0.5547934 | J14: =J8/J4 -> 0.56139184 | K14: =K8/K4 -> 0.56057839 | L14: =L8/L4 -> 0.57712169 | M14: =M8/M4 -> 0.58242624
H15: =H8-H6 -> 630 | I15: =I8-I6 -> 636 | J15: =J8-J6 -> #VALUE! | K15: =K8-K6 -> #VALUE! | L15: =L8-L6 -> #VALUE! | M15: =M8-M6 -> #VALUE!
H17: =H8-H9 -> 1883 | I17: =I8-I9 -> 1963 | J17: =J8-J9 -> 2083 | K17: =K8-K9 -> 2038 | L17: =L8-L9 -> 1775 | M17: =M8-M9 -> 1779
H18: =H17/H4 -> 0.081656548 | I18: =I17/I4 -> 0.080629261 | J18: =J17/J4 -> 0.08152961 | K18: =K17/K4 -> 0.077549467 | L18: =L17/L4 -> 0.066419698 | M18: =M17/M4 -> 0.063699513
H20: =H12/H4 -> 0.32372073 | I20: =I12/I4 -> 0.33200526 | J20: =J12/J4 -> 0.33954362 | K20: =K12/K4 -> 0.34200913 | L20: =L12/L4 -> 0.36719802 | M20: =M12/M4 -> 0.37474936
B25: Capex | C25: 1354 | D25: 1830 | E25: 1749 | F25: 2198 | G25: 2690 | H25: 2707 | I25: 2928 | J25: 3261 | K25: 3525 | L25: =K25*(1+L27) -> 3774.0819 | M25: =L25*(1+M27) -> 4040.7644
B26: % sales | C26: =C25/C4 -> 0.085452824 | D26: =D25/D4 -> 0.087854057 | E26: =E25/E4 -> 0.081935726 | F26: =F25/F4 -> 0.09247339 | G26: =G25/G4 -> 0.10705615 | H26: =H25/H4 -> 0.11738942 | I26: =I25/I4 -> 0.12026616 | J26: =J25/J4 -> 0.12763709 | K26: =K25/K4 -> 0.13413242
B27: % growth | D27: =D25/C25-1 -> 0.35155096 | E27: =E25/D25-1 -> -0.044262295 | F27: =F25/E25-1 -> 0.25671812 | G27: =G25/F25-1 -> 0.22383985 | H27: =H25/G25-1 -> 0.0063197026 | I27: =I25/H25-1 -> 0.081640192 | J27: =J25/I25-1 -> 0.11372951 | K27: =K25/J25-1 -> 0.080956762 | L27: =AVERAGE(H27:K27) -> 0.070661541 | M27: =L27 -> 0.070661541

Sheet IS
B1: McDonald's Corporation (MCD)
B2: $310.45
B5: McDonald's Corporation
B6: MCD 580135101 2550707 NYSE Common stock
B7: Source: FactSet Fundamentals
C8: DEC '15 | D8: DEC '16 | E8: DEC '17 | F8: DEC '18 | G8: DEC '19 | H8: DEC '20 | I8: DEC '21 | J8: DEC '22 | K8: DEC '23 | L8: DEC '24 | M8: SEP '25 | O8: fractin of the year recorded
M9: LTM | O9: calculate with a prop the total of the year
G10: Restate
B11: Sales | C11: 22917 | D11: 22258 | E11: 20232 | F11: 17822 | G11: 19088 | H11: 16849 | I11: 19647 | J11: 22058 | K11: 23581 | L11: 23962 | M11: 23790 | O11: =9/12 -> 0.75
B12: Cost of Goods Sold (COGS) incl. D&A | C12: 14089 | D12: 13033 | E12: 10816 | F12: 8679 | G12: 9134 | H12: 8324 | I12: 9063 | J12: 9611 | K12: 10249 | L12: 10463 | M12: 10171 | O12: =M11/O11 -> 31720
B13: COGS excluding D&A | C13: 12686 | D13: 11662 | E13: 9607 | F13: 7423 | G13: 7689 | H13: 6788 | I13: 7482 | J13: 7831 | K13: 8419 | L13: 8525 | M13: 8200
B14: Depreciation & Amortization Expense | C14: 1403 | D14: 1371 | E14: 1209 | F14: 1256 | G14: 1446 | H14: 1536 | I14: 1580 | J14: 1780 | K14: 1830 | L14: 1939 | M14: 1971
B15: Depreciation | C15: 1297 | D15: 1257 | E15: 1088 | F15: 1104 | G15: 1244 | H15: 1289 | I15: 1295 | J15: 1383 | K15: 1389 | L15: 1387
B16: Amortization of Intangibles | C16: 106 | D16: 114 | E16: 120 | F16: 152 | G16: 202 | H16: 247 | I16: 285 | J16: 396 | K16: 441 | L16: 552
B17: Gross Income | C17: 8828 | D17: 9225 | E17: 9416 | F17: 9143 | G17: 9954 | H17: 8525 | I17: 10585 | J17: 12447 | K17: 13332 | L17: 13499 | M17: 13619
B18: SG&A Expense | C18: 2195 | D18: 2156 | E18: 1978 | F18: 1865 | G18: 2021 | H18: 2243 | I18: 2316 | J18: 2595 | K18: 2492 | L18: 2535 | M18: 2640
B19: Other SG&A | C19: 2195 | D19: 2156 | E19: 1978 | F19: 1865 | G19: 2021 | H19: 2243 | I19: 2316 | J19: 2595 | K19: 2492 | L19: 2535 | M19: 2640
B20: EBIT (Operating Income) | C20: 6632 | D20: 7069 | E20: 7438 | F20: 7278 | G20: 7932 | H20: 6283 | I20: 8269 | J20: 9852 | K20: 10840 | L20: 10964 | M20: 10978
B21: Nonoperating Income - Net | C21: -2 | D21: 218 | E21: 296 | F21: 356 | G21: 267 | H21: -82 | I21: 118 | J21: -1263 | K21: 861 | L21: 272 | M21: 2168
B22: Nonoperating Interest Income | C22: 9 | D22: 4 | E22: 6 | F22: 3 | G22: 33 | H22: 16 | I22: 8 | J22: 42 | K22: 172 | L22: 95 | M22: 73
B23: Equity in Earnings of Affiliates | C23: -132 | D23: 50 | E23: 163 | F23: 128 | G23: 137 | H23: 103 | I23: 149 | J23: 108 | K23: 142 | L23: 145 | M23: 176
B24: Other Income (Expense) | C24: 121 | D24: 165 | E24: 127 | F24: 224 | G24: 97 | H24: -201 | I24: -39 | J24: -1413 | K24: 547 | L24: 31 | M24: 1919
B25: Interest Expense | C25: 575 | D25: 799 | E25: 816 | F25: 831 | G25: 1057 | H25: 1075 | I25: 1010 | J25: 1236 | K25: 1297 | L25: 1435 | M25: 1460
B26: Gross Interest Expense | C26: 584 | D26: 806 | E26: 821 | F26: 835 | G26: 1063 | H26: 1080 | I26: 1016 | J26: 1245 | K26: 1303 | L26: 1443 | M26: 1460
B27: Interest Capitalized | C27: 8 | D27: 6 | E27: 5 | F27: 5 | G27: 7 | H27: 5 | I27: 6 | J27: 9 | K27: 6 | L27: 8
B28: Unusual Expense - Net | C28: 143 | D28: 281 | E28: -684 | F28: 177 | G28: -21 | H28: -261 | I28: -346 | J28: -94 | K28: 671 | L28: 238 | M28: 2015
B29: Restructuring Expense | C29: 212 | D29: 309 | E29: -623 | F29: 196 | G29: 66 | H29: -235 | I29: -241 | J29: 961 | K29: 335 | L29: 268 | M29: 138
B30: Unrealized Valuation Gain/Loss | C30: 69 | D30: 27 | E30: 61 | F30: 19 | G30: 87 | H30: 26 | I30: 104 | J30: 1055 | K30: -336 | L30: 31 | M30: -1878
B31: Hedges/Derivatives | C31: 69 | D31: 27 | E31: 61 | F31: 19 | G31: 87 | H31: 26 | I31: 104 | J31: 1055 | K31: -336 | L31: 31 | M31: -1878
B32: Pretax Income | C32: 5912 | D32: 6207 | E32: 7601 | F32: 6625 | G32: 7164 | H32: 5387 | I32: 7723 | J32: 7446 | K32: 9733 | L32: 9564 | M32: 9671
B33: Income Taxes | C33: 1827 | D33: 1970 | E33: 2998 | F33: 1604 | G33: 1780 | H33: 1237 | I33: 1339 | J33: 1568 | K33: 1899 | L33: 1961 | M33: 2048
B34: Income Taxes - Current Domestic | C34: 1093 | D34: 1056 | E34: 1951 | F34: 404 | G34: 640 | H34: 591 | I34: 944 | J34: 727 | K34: 1482 | L34: 1554
B35: Income Taxes - Current Foreign | C35: 736 | D35: 1401 | E35: 1079 | F35: 1112 | G35: 1006 | H35: 641 | I35: 757 | J35: 1170 | K35: 1052 | L35: 937
B36: Income Taxes - Deferred Domestic | C36: 3 | D36: -98 | E36: -95 | F36: 139 | G36: 52 | H36: 828 | I36: -170 | J36: -120 | K36: -162 | L36: -89
B37: Income Taxes - Deferred Foreign | C37: -4 | D37: -389 | E37: 63 | F37: -52 | G37: 81 | H37: -822 | I37: -192 | J37: -209 | K37: -472 | L37: -442
B38: Consolidated Net Income | C38: 4084 | D38: 4237 | E38: 4603 | F38: 5022 | G38: 5383 | H38: 4150 | I38: 6384 | J38: 5878 | K38: 7833 | L38: 7602 | M38: 7623
B39: Net Income | C39: 4084 | D39: 4237 | E39: 4603 | F39: 5022 | G39: 5383 | H39: 4150 | I39: 6384 | J39: 5878 | K39: 7833 | L39: 7602 | M39: 7623
B40: Net Income available to Common | C40: 4084 | D40: 4237 | E40: 4603 | F40: 5022 | G40: 5383 | H40: 4150 | I40: 6384 | J40: 5878 | K40: 7833 | L40: 7602 | M40: 7623
B41: Per Share
B42: EPS (recurring) | C42: 4.43 | D42: 5.15 | E42: 5.06 | F42: 6.55 | G42: 7.02 | H42: 5.29 | I42: 8.17 | J42: 7.84 | K42: 11.34 | L42: 10.76 | M42: 12.62
B43: EPS (basic) | C43: 4.35 | D43: 4.96 | E43: 5.7 | F43: 6.45 | G43: 7.1 | H43: 5.57 | I43: 8.55 | J43: 7.98 | K43: 10.76 | L43: 10.58 | M43: 10.67
B44: Basic Shares Outstanding | C44: 939.4 | D44: 854.4 | E44: 807.4 | F44: 778.2 | G44: 758.1 | H44: 744.6 | I44: 746.3 | J44: 736.5 | K44: 727.9 | L44: 718.3 | M44: 712.9
B45: Total Shares Outstanding | C45: 906.8 | D45: 819.3 | E45: 794.1 | F45: 767.1 | G45: 746.3 | H45: 745.4 | I45: 745.4 | J45: 744.8 | K45: 731.3 | L45: 715.2 | M45: 712.1
B46: EPS (diluted) | C46: 4.33 | D46: 4.92 | E46: 5.65 | F46: 6.39 | G46: 7.04 | H46: 5.53 | I46: 8.49 | J46: 7.93 | K46: 10.7 | L46: 10.53 | M46: 10.62
B47: Diluted Shares Outstanding | C47: 944.6 | D47: 861.2 | E47: 815.5 | F47: 785.6 | G47: 764.9 | H47: 750.1 | I47: 751.8 | J47: 741.3 | K47: 732.3 | L47: 721.9 | M47: 715.9
B48: Total Shares Outstanding | C48: 906.8 | D48: 819.3 | E48: 794.1 | F48: 767.1 | G48: 746.3 | H48: 745.4 | I48: 745.4 | J48: 744.8 | K48: 731.3 | L48: 715.2 | M48: 712.1
B49: Earnings Persistence | C49: 88.03 | D49: 91.89 | E49: 88.7 | F49: 90.97 | G49: 75.15 | H49: 92.54 | I49: 95.26 | J49: 93.07 | K49: 86.94 | L49: 85.76
B50: Dividends per Share | C50: 3.1 | D50: 3.26 | E50: 3.4 | F50: 3.55 | G50: 4.23 | H50: 4.42 | I50: 4.44 | J50: 5.39 | K50: 5.76 | L50: 6.27 | M50: 6.41
B51: Payout Ratio | C51: 71.67 | D51: 66.36 | E51: 60.13 | F51: 55.57 | G51: 60.05 | H51: 79.92 | I51: 52.31 | J51: 67.92 | K51: 53.87 | L51: 59.52 | M51: 60.38
B52: EBITDA
B53: EBITDA | C53: 8035 | D53: 8440 | E53: 8647 | F53: 8534 | G53: 9378 | H53: 7819 | I53: 9849 | J53: 11632 | K53: 12669 | L53: 12903 | M53: 12949
B54: EBIT | C54: 6632 | D54: 7069 | E54: 7438 | F54: 7278 | G54: 7932 | H54: 6283 | I54: 8269 | J54: 9852 | K54: 10840 | L54: 10964 | M54: 10978
B55: Depreciation & Amortization Expense | C55: 1403 | D55: 1371 | E55: 1209 | F55: 1256 | G55: 1446 | H55: 1536 | I55: 1580 | J55: 1780 | K55: 1830 | L55: 1939 | M55: 1971
B56: All figures in millions of Euro except per share items.

Sheet BS
B4: McDonald's Corporation
B5: MCD 580135101 2550707 NYSE Common stock
B6: Source: FactSet Fundamentals
C7: DEC '15 | D7: DEC '16 | E7: DEC '17 | F7: DEC '18 | G7: DEC '19 | H7: DEC '20 | I7: DEC '21 | J7: DEC '22 | K7: DEC '23 | L7: DEC '24
G8: Restate
B9: Assets
B10: Cash & Short-Term Investments | C10: 7074.9332 | D10: 1159.8957 | E10: 2051.7988 | F10: 757.55587 | G10: 800.44544 | H10: 2818.9285 | I10: 4141.0482 | J10: 2420.9885 | K10: 4145.4761 | L10: 1047.803
B11: Cash Only | C11: 7074.9332 | D11: 1159.8957 | E11: 2051.7988 | F11: 757.55587 | G11: 800.44544 | H11: 2818.9285 | I11: 4141.0482 | J11: 2420.9885 | K11: 4145.4761 | L11: 1047.803
B12: Short-Term Receivables | C12: 1195.5261 | D12: 1397.5824 | E12: 1645.7362 | F12: 2135.7652 | G12: 1981.4699 | H12: 1724.7354 | I12: 1646.5002 | J12: 1981.7287 | K12: 2252.2972 | L12: 2301.3037
B13: Accounts Receivables, Net | C13: 1195.5261 | D13: 1397.5824 | E13: 1645.7362 | F13: 2135.7652 | G13: 1981.4699 | H13: 1724.7354 | I13: 1646.5002 | J13: 1981.7287 | K13: 2252.2972 | L13: 2301.3037
B14: Accounts Receivables, Gross | C14: 1195.5261 | D14: 1397.5824 | E14: 1645.7362 | F14: 2135.7652 | G14: 1981.4699 | H14: 1724.7354 | I14: 1646.5002 | J14: 1981.7287 | K14: 2252.2972 | L14: 2301.3037
B15: Inventories | C15: 92.147656 | D15: 55.842618 | E15: 48.967356 | F15: 44.701045 | G15: 44.721604 | H15: 41.76372 | I15: 48.892016 | J15: 48.723354 | K15: 47.797947 | L15: 54.080153
B16: Finished Goods | C16: 92.147656 | D16: 55.842618 | E16: 48.967356 | F16: 44.701045 | G16: 44.721604 | H16: 41.76372 | I16: 48.892016 | J16: 48.723354
B17: Other Current Assets | C17: 514.31464 | D17: 1983.598 | E17: 689.87342 | F17: 607.61929 | G17: 342.98441 | H17: 517.10188 | I17: 449.61309 | J17: 630.96744 | K17: 784.23032 | L17: 1037.1801
B18: Miscellaneous Current Assets | C18: 514.31464 | D18: 1983.598 | E18: 689.87342 | F18: 607.61929 | G18: 342.98441 | H18: 517.10188 | I18: 449.61309 | J18: 630.96744 | K18: 784.23032 | L18: 1037.1801
B19: Total Current Assets | C19: 8876.9216 | D19: 4596.9188 | E19: 4436.3758 | F19: 3545.6414 | G19: 3169.6214 | H19: 5102.5295 | I19: 6286.0535 | J19: 5082.408 | K19: 7229.8015 | L19: 4440.3668
B20: Net Property, Plant & Equipment | C20: 21281.046 | D20: 20154.16 | E20: 18694.454 | F20: 19982.242 | G20: 33337.372 | H20: 31699.481 | I20: 33655.118 | J20: 34049.473 | K20: 34782.059 | L20: 37309.511
B21: Property, Plant & Equipment - Gross | C21: 34697.965 | D21: 32655.511 | E21: 30501.666 | F21: 32536.062 | G21: 46603.208 | H21: 45199.788 | I21: 48776.469 | J21: 50225.626 | K21: 51676.46 | L21: 55544.18
B22: Buildings | C22: 24767.191 | D22: 23898.649 | E22: 22723.268 | F22: 24704.544 | G22: 26378.263 | H22: 25812.921 | I22: 28094.707 | J22: 29445.959 | K22: 30219.165 | L22: 32741.67
B23: Land & Improvements | C23: 5139.0039 | D23: 5181.3227 | E23: 4715.3565 | F23: 4829.9873 | G23: 5368.7306 | H23: 5189.081 | I23: 5704.8893 | J23: 6264.98 | K23: 6410.4469 | L23: 7004.3455
B24: Machinery & Equipment | C24: 4288.4102 | D24: 3101.1141 | E24: 2636.3258 | F24: 2574.1153 | G24: 2667.706 | H24: 2549.1398 | I24: 2666.1977 | J24: 2341.1572 | K24: 2437.6047 | L24: 2497.3442
B25: Other Property, Plant & Equipment | C25: 503.36003 | D25: 474.42523 | E25: 426.71553 | F25: 427.41547 | G25: 374.52116 | H25: 347.34992 | I25: 393.68625 | J25: 399.6252 | K25: 375.14146 | L25: 419.12119
B26: Operating Lease Right-of-Use Assets | G26: 11813.987 | H26: 11301.295 | I26: 11916.989 | J26: 11773.905 | K26: 12234.102 | L26: 12881.699
B27: Accumulated Depreciation | C27: 13416.92 | D27: 12501.351 | E27: 11807.212 | F27: 12553.82 | G27: 13265.835 | H27: 13500.307 | I27: 15121.351 | J27: 16176.154 | K27: 16894.401 | L27: 18234.669
B28: Total Long-Term Investments | C28: 863.94181 | D28: 692.20196 | E28: 1043.5543 | F28: 1055.5045 | G28: 1310.4677 | H28: 1089.4528 | I28: 1264.5973 | J28: 1024.3148 | K28: 1150.7718 | L28: 2655.7218
B29: LT Investment - Affiliate Companies | C29: 729.72475 | D29: 688.21997 | E29: 904.14724 | F29: 1052.1804 | G29: 1131.6704 | H29: 1060.1937 | I29: 1056.2786 | J29: 997.42328 | K29: 977.86632 | L29: 2617.0931
B30: Other Long-Term Investments | C30: 134.21707 | D30: 3.981986 | E30: 139.40706 | F30: 3.324148 | G30: 178.79733 | H30: 29.259123 | I30: 208.31868 | J30: 26.891544 | K30: 172.90545 | L30: 38.628681
B31: Intangible Assets | C31: 2316.3951 | D31: 2215.2169 | E31: 1981.7622 | F31: 2039.5398 | G31: 2977.9956 | H31: 2831.3514 | I31: 3145.8847 | J31: 3527.4771 | K31: 3509.1659 | L31: 3913.0854
B32: Goodwill | C32: 2316.3951 | D32: 2215.2169 | E32: 1981.7622 | F32: 2039.5398 | G32: 2385.2116 | H32: 2266.4378 | I32: 2446.7992 | J32: 2717.6388 | K32: 2752.3651 | L32: 3037.18
B33: Other Intangible Assets | C33: 0 | D33: 0 | E33: 0 | F33: 0 | G33: 592.78397 | H33: 564.91357 | I33: 699.08548 | J33: 809.83836 | K33: 756.80082 | L33: 875.90534
B34: Deferred Tax Assets | C34: 490.47224 | D34: 762.26595 | E34: 722.76816 | F34: 1066.7016 | G34: 1014.6103 | H34: 1745.4947 | I34: 2072.6346 | J34: 2320.9182 | K34: 2736.523 | L34: 3421.5354
B35: Other Assets | C35: 1095.9219 | D35: 992.74712 | E35: 1272.0686 | F35: 1012.8155 | G35: 515.81292 | H35: 543.25528 | I35: 932.64159 | J35: 1252.9398 | K35: 1419.3636 | L35: 1549.9758
B36: Tangible Other Assets | C36: 1095.9219 | D36: 992.74712 | E36: 1272.0686 | F36: 1012.8155 | G36: 515.81292 | H36: 543.25528 | I36: 932.64159 | J36: 1252.9398 | K36: 1419.3636 | L36: 1549.9758
B37: Total Assets | C37: 34924.698 | D37: 29413.511 | E37: 28150.983 | F37: 28702.445 | G37: 42325.88 | H37: 43011.565 | I37: 47356.93 | J37: 47257.531 | K37: 50827.685 | L37: 53290.196
B38: Liabilities & Shareholders' Equity
B39: Current
B40: ST Debt & Curr. Portion LT Debt | C40: 0 | D40: 73.192701 | E40: 0 | F40: 0 | G40: 605.87974 | H40: 2407.0124 | I40: 620.38341 | J40: 619.44249 | K40: 2607.6134 | L40: 614.19602
B41: Accounts Payable | C41: 805.21034 | D41: 716.75754 | E41: 770.15324 | F41: 1056.6417 | G41: 880.35636 | H41: 605.86 | I41: 885.33241 | J41: 918.43522 | K41: 998.41582 | L41: 993.72281
B42: Income Tax Payable | C42: 142.50207 | D42: 253.33018 | E42: 221.35243 | F42: 199.71132 | G42: 295.50112 | H42: 605.69654 | I42: 317.18256 | J42: 257.57788 | K42: 638.30174 | L42: 348.62384
B43: Other Current Liabilities | C43: 1768.296 | D43: 2244.987 | E43: 1415.7229 | F43: 1344.7929 | G43: 1444.098 | H43: 1433.2884 | I43: 1712.0999 | J43: 1767.0649 | K43: 1964.8758 | L43: 1772.0907
B44: Accrued Payroll | C44: 1243.4871 | D44: 1095.4255 | E44: 923.05131 | F44: 859.99212 | G44: 913.67484 | H44: 862.89894 | I44: 1181.5864 | J44: 1141.1572 | K44: 1256.4161 | L44: 1083.5345
B45: Miscellaneous Current Liabilities | C45: 524.80898 | D45: 1149.5615 | E45: 492.67156 | F45: 484.80076 | G45: 530.42317 | H45: 570.38944 | I45: 530.51355 | J45: 625.9077 | K45: 708.45971 | L45: 688.55623
B46: Total Current Liabilities | C46: 2716.0084 | D46: 3288.2674 | E46: 2407.2285 | F46: 2601.1459 | G46: 3225.8352 | H46: 5051.8573 | I46: 3534.9983 | J46: 3562.5205 | K46: 6209.2067 | L46: 3728.6334
B47: Long-Term
B48: Long-Term Debt | C48: 22205.744 | D48: 24535.198 | E48: 24597.269 | F48: 27183.921 | G48: 41760.268 | H48: 39653.549 | I48: 42774.886 | J48: 45010.916 | K48: 45453.856 | L48: 49552.872
B49: Long-Term Debt excl Lease Obligations | C49: 22205.744 | D49: 24535.198 | E49: 24597.269 | F49: 27183.921 | G49: 30394.744 | H49: 28766.131 | I49: 31324.921 | J49: 33641.134 | K49: 33633.188 | L49: 37106.711
B50: Capital and Operating Lease Obligations | C50: 0 | D50: 0 | E50: 0 | F50: 0 | G50: 11365.523 | H50: 10887.418 | I50: 11449.965 | J50: 11369.782 | K50: 11820.668 | L50: 12446.161
B51: Deferred Tax Liabilities | C51: 1568.9036 | D51: 1722.7779 | E51: 932.21187 | F51: 1063.29 | G51: 1174.2539 | H51: 1655.5106 | I51: 1825.1847 | J51: 1871.6327 | K51: 1521.6585 | L51: 1848.3824
B52: Other Liabilities | C52: 1909.2332 | D52: 1957.1463 | E52: 2935.7928 | F52: 3328.7845 | G52: 3479.8218 | H52: 3045.8911 | I52: 3267.763 | J52: 2437.5732 | K52: 1903.7705 | L52: 1827.1366
B53: Other Liabilities (excl. Deferred Income) | C53: 1909.2332 | D53: 1957.1463 | E53: 2935.7928 | F53: 2779.6002 | G53: 2891.3141 | H53: 2472.1507 | I53: 2618.5368 | J53: 1727.524 | K53: 1188.5213 | L53: 1075.8088
B54: Deferred Income | F54: 549.18426 | G54: 588.5078 | H54: 573.74035 | I54: 649.22618 | J54: 710.04919 | K54: 715.2492 | L54: 751.32784
B55: Total Liabilities | C55: 28399.889 | D55: 31503.39 | E55: 30872.502 | F55: 34177.142 | G55: 49640.179 | H55: 49406.808 | I55: 51402.832 | J55: 52882.642 | K55: 55088.491 | L55: 56957.024
B56: Equity
B57: Common Equity | C57: 6524.8089 | D57: -2089.8792 | E57: -2721.519 | F57: -5474.697 | G57: -7314.2985 | H57: -6395.2434 | I57: -4045.9023 | J57: -5625.1112 | K57: -4260.8067 | L57: -3666.8275
B58: Common Stock Par/Carry Value | C58: 15.28123 | D58: 15.738327 | E58: 13.824117 | F58: 14.521279 | G58: 14.788419 | H58: 13.567079 | I58: 14.597257 | J58: 15.553994 | K58: 15.027385 | L58: 16.417189
B59: Additional Paid-In Capital/Capital Surplus | C59: 6014.3606 | D59: 6407.1108 | E59: 5889.7402 | F59: 6452.3465 | G59: 6818.6192 | H59: 6459.5644 | I59: 7238.4806 | J59: 8008.5265 | K59: 8050.4235 | L59: 8962.8196
B60: Retained Earnings | C60: 41051.735 | D60: 43823.371 | E60: 40244.671 | F60: 44164.807 | G60: 47154.121 | H60: 44058.764 | I60: 50593.3 | J60: 55791.895 | K60: 57466.077 | L60: 64542.731
B61: Cumulative Translation Adjustment/Unrealized For. Exch. Gain | C61: -2513.0258 | D61: -2757.7152 | E61: -1641.9887 | F61: -2121.5938 | G61: -2005.3452 | H61: -1788.1574 | I61: -2083.5385 | J61: -2079.2691 | K61: -1885.6652 | L61: -2200.8691
B62: Other Appropriated Reserves | C62: -137.99135 | D62: -174.63854 | E62: -172.13524 | F62: -161.13371 | G62: -206.41426 | H62: -326.01855 | I62: -179.65178 | J62: -250.64418 | K62: -337.66352 | L62: -264.60646
B63: Treasury Stock | C63: -37905.551 | D63: -49403.746 | E63: -47055.63 | F63: -53823.644 | G63: -59090.067 | H63: -54812.962 | I63: -59629.09 | J63: -67111.173 | K63: -67569.006 | L63: -74722.354
B64: Total Shareholders' Equity | C64: 6524.8089 | D64: -2089.8792 | E64: -2721.519 | F64: -5474.697 | G64: -7314.2985 | H64: -6395.2434 | I64: -4045.9023 | J64: -5625.1112 | K64: -4260.8067 | L64: -3666.8275
B65: Total Equity | C65: 6524.8089 | D65: -2089.8792 | E65: -2721.519 | F65: -5474.697 | G65: -7314.2985 | H65: -6395.2434 | I65: -4045.9023 | J65: -5625.1112 | K65: -4260.8067 | L65: -3666.8275
B66: Total Liabilities & Shareholders' Equity | C66: 34924.698 | D66: 29413.511 | E66: 28150.983 | F66: 28702.445 | G66: 42325.88 | H66: 43011.565 | I66: 47356.93 | J66: 47257.531 | K66: 50827.685 | L66: 53290.196
B67: Per Share
B68: Book Value per Share | C68: 7.19542 | D68: -2.55081 | E68: -3.42717 | F68: -7.13688 | G68: -9.80075 | H68: -8.57961 | I68: -5.42783 | J68: -7.55251 | K68: -5.82635 | L68: -5.127
B69: Tangible Book Value per Share | C69: 4.64095 | D69: -5.254603 | E69: -5.922782 | F69: -9.795642 | G69: -13.791095 | H69: -12.378045 | I69: -9.648225 | J69: -12.288652 | K69: -10.624877 | L69: -10.598312
B70: All figures in millions of Euro except per share items.
