Workbook
Name D: WACC!$D$15
Name D_perc: WACC!$D$17
Name E: WACC!$D$14
Name E_perc: WACC!$D$16
Name kd: WACC!$D$19
Name ke: WACC!$D$12
Name scen: 'DCF model'!$E$16
Name Tax_shield: WACC!$D$18
Name Tax_shielf: WACC!$D$18
Name Tgr: 'DCF model'!$E$18
Name wacc: 'DCF model'!$E$17

Sheet Agenda
C3: Agenda
B6: 1 | C6: DCF | E6: X
B7: 2 | C7: Comps analysis
B8: 3 | C8: Past transactions
B9: 3 | C9: Football chart

Sheet DCF model
C3: DCF model
A6: • | C6: Overview
C8: Comp name | E8: McDonald's Corporation | G8: Valuation | I8: =R98 -> 270.50981
C9: Ticker | E9: MCD | G9: % delta vs current | I9: =I8/E11-1 -> -0.12865256
C10: Date | E10: =TODAY() -> 45986
C11: Price per share | E11: 310.45
A13: • | C13: Assumptions
C15: Triggers | G15: Conservative | H15: Year | I15: Amount | K15: Base / Street | L15: Year | M15: Amount | O15: Optimistic | P15: Year | Q15: Amount
C16: Scenario | E16: 1 | G16: Revenue gr | H16: 25-'30 | I16: -0.2 | O16: Revenue gr | P16: 25-'30 | Q16: 0.55
C17: WACC | E17: =CHOOSE(scen,M20,I20,Q20) -> 0.061305018 | G17: EBITDA margin | H17: 25 | I17: -0.05 | O17: EBITDA margin | P17: 25 | Q17: 0
C18: TGR | E18: =CHOOSE(scen,M21,I21,Q21) -> 0.025 | G18: EBITDA margin | H18: 30 | I18: -0.15 | O18: EBITDA margin | P18: 30 | Q18: 0.05
G19: D&A | H19: 25 | I19: 0 | O19: D&A | P19: 25-'30 | Q19: 0
G20: WACC | I20: 0.062 | K20: WACC | M20: =WACC!D21 -> 0.061305018 | O20: WACC | Q20: 0.06
G21: TGR | I21: 0.022 | K21: TGR | M21: 0.025 | O21: TGR | Q21: 0.028
A23: • | C23: Income statement
H25: Actuals | M25: Projections
C26: $M | H26: 2020 | I26: =+H26+1 -> 2021 | J26: =+I26+1 -> 2022 | K26: =+J26+1 -> 2023 | L26: =+K26+1 -> 2024 | M26: =+L26+1 -> 2025 | N26: =+M26+1 -> 2026 | O26: =+N26+1 -> 2027 | P26: =+O26+1 -> 2028 | ... R26: =+Q26+1 -> 2030
C27: Revenue | H27: =IS!H11 -> 16849 | I27: =IS!I11 -> 19647 | J27: =IS!J11 -> 22058 | K27: =IS!K11 -> 23581 | L27: =IS!L11 -> 23962 | M27: =L27*(1+M28) -> 24561.05 | N27: =M27*(1+N28) -> 25175.076 | O27: =N27*(1+O28) -> 25804.453 | P27: =O27*(1+P28) -> 26449.564 | Q27: =P27*(1+Q28) -> 27110.804 | R27: =Q27*(1+R28) -> 27788.574
C28: % growth | I28: =I27/H27-1 -> 0.16606327 | J28: =J27/I27-1 -> 0.12271594 | K28: =K27/J27-1 -> 0.069045244 | L28: =L27/K27-1 -> 0.016157076 | M28: =OFFSET(M28,scen,0) -> 0.025 | N28: =OFFSET(N28,scen,0) -> 0.025 | O28: =OFFSET(O28,scen,0) -> 0.025 | P28: =OFFSET(P28,scen,0) -> 0.025 | Q28: =OFFSET(Q28,scen,0) -> 0.025 | R28: =OFFSET(R28,scen,0) -> 0.025
C29: 1. Base | M29: 0.025 | N29: =M29 -> 0.025 | O29: =N29 -> 0.025 | P29: =O29 -> 0.025 | Q29: =P29 -> 0.025 | R29: =Q29 -> 0.025
C30: 2. Conservative | M30: =M29*(1+I16) -> 0.02 | N30: =M30 -> 0.02 | O30: =N30 -> 0.02 | P30: =O30 -> 0.02 | Q30: =P30 -> 0.02 | R30: =Q30 -> 0.02
C31: 3. Optimistic | M31: =M29*(1+Q16) -> 0.03875 | N31: =M31 -> 0.03875 | O31: =N31 -> 0.03875 | P31: =O31 -> 0.03875 | Q31: =P31 -> 0.03875 | R31: =Q31 -> 0.03875
C33: COGS | H33: =IS!H13*-1 -> -6788 | I33: =IS!I13*-1 -> -7482 | J33: =IS!J13*-1 -> -7831 | K33: =IS!K13*-1 -> -8419 | L33: =IS!L13*-1 -> -8525 | M33: =M35-M27 -> -8524.4558 | N33: =N35-N27 -> -8540.3171 | O33: =O35-O27 -> -8583.3187 | P33: =P35-P27 -> -8621.3851 | Q33: =Q35-Q27 -> -8654.1808 | R33: =R35-R27 -> -8681.355
C35: Gross profit | H35: =H27+H33 -> 10061 | I35: =I27+I33 -> 12165 | J35: =J27+J33 -> 14227 | K35: =K27+K33 -> 15162 | L35: =L27+L33 -> 15437 | M35: =M27*M36 -> 16036.594 | N35: =N27*N36 -> 16634.759 | O35: =O27*O36 -> 17221.134 | P35: =P27*P36 -> 17828.179 | Q35: =Q27*Q36 -> 18456.623 | R35: =R27*R36 -> 19107.219
C36: % margin | H36: =H35/H$27 -> 0.59712743 | I36: =I35/I$27 -> 0.6191785 | J36: =J35/J$27 -> 0.64498141 | K36: =K35/K$27 -> 0.64297528 | L36: =L35/L$27 -> 0.64422836 | M36: =L36*(1+M37) -> 0.65292788 | N36: =M36*(1+N37) -> 0.66076301 | O36: =N36*(1+O37) -> 0.66737064 | P36: =O36*(1+P37) -> 0.67404435 | Q36: =P36*(1+Q37) -> 0.68078479 | R36: =Q36*(1+R37) -> 0.68759264
C37: % growth | I37: =I36/H36-1 -> 0.036928591 | J37: =J36/I36-1 -> 0.041672817 | K37: =K36/J36-1 -> -0.0031103779 | L37: =L36/K36-1 -> 0.001948885 | M37: =OFFSET(M37,scen,0) -> 0.013503775 | N37: =OFFSET(N37,scen,0) -> 0.012 | O37: =OFFSET(O37,scen,0) -> 0.01 | P37: =OFFSET(P37,scen,0) -> 0.01 | Q37: =OFFSET(Q37,scen,0) -> 0.01 | R37: =OFFSET(R37,scen,0) -> 0.01
C38: 1. Base | M38: =AVERAGE(J37:L37) -> 0.013503775 | N38: 0.012 | O38: 0.01 | P38: =O38 -> 0.01 | Q38: =P38 -> 0.01 | R38: =Q38 -> 0.01
C39: 2. Conservative | M39: =AVERAGE(K37:L37) -> -0.00058074646 | N39: =M39 -> -0.00058074646 | O39: =N39 -> -0.00058074646 | P39: 0 | Q39: 0 | R39: 0
C40: 3. Optimistic | M40: 0.03 | N40: =M40 -> 0.03 | O40: =N40 -> 0.03 | P40: =O40 -> 0.03 | Q40: =P40 -> 0.03 | R40: =Q40 -> 0.03
C42: Opex | H42: =IS!H18*-1 -> -2243 | I42: =IS!I18*-1 -> -2316 | J42: =IS!J18*-1 -> -2595 | K42: =IS!K18*-1 -> -2492 | L42: =IS!L18*-1 -> -2535 | M42: =M45-M35 -> -2564.2299 | N42: =N45-N35 -> -2667.7931 | O42: =O45-O35 -> -2734.7251 | P42: =P45-P35 -> -3001.1252 | Q42: =Q45-Q35 -> -2810.39 | R42: =R45-R35 -> -2922.4242
C43: % sales | H43: =H42/H27*-1 -> 0.13312363 | I43: =I42/I27*-1 -> 0.11788059 | J43: =J42/J27*-1 -> 0.11764439 | K43: =K42/K27*-1 -> 0.1056783 | L43: =L42/L27*-1 -> 0.1057925 | M43: =M42/M27*-1 -> 0.10440229 | N43: =N42/N27*-1 -> 0.10596962 | O43: =O42/O27*-1 -> 0.10597881 | ... R43: =R42/R27*-1 -> 0.1051664
C45: EBITDA | H45: =H35+H42 -> 7818 | I45: =I35+I42 -> 9849 | J45: =J35+J42 -> 11632 | K45: =K35+K42 -> 12670 | L45: =L35+L42 -> 12902 | M45: =M27*M46 -> 13472.364 | N45: =N27*N46 -> 13966.966 | O45: =O27*O46 -> 14486.409 | P45: =P27*P46 -> 14827.054 | Q45: =Q27*Q46 -> 15646.233 | R45: =R27*R46 -> 16184.794
C46: % margin | H46: =H45/H$27 -> 0.4640038 | I46: =I45/I$27 -> 0.50129791 | J46: =J45/J$27 -> 0.52733702 | K46: =K45/K$27 -> 0.53729698 | L46: =L45/L$27 -> 0.53843586 | M46: =OFFSET(M46,scen,0) -> 0.54852559 | N46: =OFFSET(N46,scen,0) -> 0.5547934 | O46: =OFFSET(O46,scen,0) -> 0.56139184 | P46: =OFFSET(P46,scen,0) -> 0.56057839 | Q46: =OFFSET(Q46,scen,0) -> 0.57712169 | R46: =OFFSET(R46,scen,0) -> 0.58242624
C47: 1. Base | M47: ='Estimates IS'!H14 -> 0.54852559 | N47: ='Estimates IS'!I14 -> 0.5547934 | O47: ='Estimates IS'!J14 -> 0.56139184 | P47: ='Estimates IS'!K14 -> 0.56057839 | Q47: ='Estimates IS'!L14 -> 0.57712169 | R47: ='Estimates IS'!M14 -> 0.58242624
C48: 2. Conservative | M48: =M47*(1+I17) -> 0.52109931 | N48: =M48-(($M$48-$R$48)/($R$26-$M$26)) -> 0.51589191 | O48: =N48-(($M$48-$R$48)/($R$26-$M$26)) -> 0.5106845 | P48: =O48-(($M$48-$R$48)/($R$26-$M$26)) -> 0.5054771 | Q48: =P48-(($M$48-$R$48)/($R$26-$M$26)) -> 0.5002697 | R48: =R47*(1+I18) -> 0.4950623
C49: 3. Optimistic | M49: =M47*(1+Q17) -> 0.54852559 | N49: =M49+(($R$49-$M$49)/($R$26-$M$26)) -> 0.56112998 | O49: =N49+(($R$49-$M$49)/($R$26-$M$26)) -> 0.57373437 | P49: =O49+(($R$49-$M$49)/($R$26-$M$26)) -> 0.58633876 | Q49: =P49+(($R$49-$M$49)/($R$26-$M$26)) -> 0.59894316 | R49: =R47*(1+Q18) -> 0.61154755
C51: D&A | H51: =IS!H14*-1 -> -1536 | I51: =IS!I14*-1 -> -1580 | J51: =IS!J14*-1 -> -1780 | K51: =IS!K14*-1 -> -1830 | L51: =IS!L14*-1 -> -1939 | M51: =M27*M52*-1 -> -2005.5706 | N51: =N27*N52*-1 -> -2029.8478 | O51: =O27*O52*-1 -> -2103.827 | P51: =P27*P52*-1 -> -2051.1496 | Q51: =Q27*Q52*-1 -> -1800.6914 | R51: =R27*R52*-1 -> -1770.1186
C52: % sales | H52: =H51/H$27*-1 -> 0.09116268 | I52: =I51/I$27*-1 -> 0.080419402 | J52: =J51/J$27*-1 -> 0.080696346 | K52: =K51/K$27*-1 -> 0.077604851 | L52: =L51/L$27*-1 -> 0.08091979 | M52: =OFFSET(M52,scen,0) -> 0.081656548 | N52: =OFFSET(N52,scen,0) -> 0.080629261 | O52: =OFFSET(O52,scen,0) -> 0.08152961 | P52: =OFFSET(P52,scen,0) -> 0.077549467 | Q52: =OFFSET(Q52,scen,0) -> 0.066419698 | R52: =OFFSET(R52,scen,0) -> 0.063699513
C53: 1. Base | M53: ='Estimates IS'!H18 -> 0.081656548 | N53: ='Estimates IS'!I18 -> 0.080629261 | O53: ='Estimates IS'!J18 -> 0.08152961 | P53: ='Estimates IS'!K18 -> 0.077549467 | Q53: ='Estimates IS'!L18 -> 0.066419698 | R53: ='Estimates IS'!M18 -> 0.063699513
C54: 2. Conservative | M54: =M53*(1+I19) -> 0.081656548 | N54: =M54 -> 0.081656548 | O54: =N54 -> 0.081656548 | P54: =O54 -> 0.081656548 | Q54: =P54 -> 0.081656548 | R54: =Q54 -> 0.081656548
C55: 3. Optimistic | M55: =M53*(1+Q19) -> 0.081656548 | N55: =N53*(1+R19) -> 0.080629261 | O55: =O53*(1+S19) -> 0.08152961 | P55: =P53*(1+T19) -> 0.077549467 | Q55: =Q53*(1+U19) -> 0.066419698 | R55: =R53*(1+V19) -> 0.063699513
C57: EBIT | H57: =H45+H51 -> 6282 | I57: =I45+I51 -> 8269 | J57: =J45+J51 -> 9852 | K57: =K45+K51 -> 10840 | L57: =L45+L51 -> 10963 | M57: =M45+M51 -> 11466.794 | N57: =N45+N51 -> 11937.118 | O57: =O45+O51 -> 12382.582 | ... R57: =R45+R51 -> 14414.676
C58: % margin | H58: =H57/H$27 -> 0.37284112 | I58: =I57/I$27 -> 0.42087851 | J58: =J57/J$27 -> 0.44664067 | K58: =K57/K$27 -> 0.45969213 | L58: =L57/L$27 -> 0.45751607 | M58: =M57/M$27 -> 0.46686904 | N58: =N57/N$27 -> 0.47416413 | O58: =O57/O$27 -> 0.47986223 | ... R58: =R57/R$27 -> 0.51872673
C60: Interests | H60: =IS!H25*-1 -> -1075 | I60: =IS!I25*-1 -> -1010 | J60: =IS!J25*-1 -> -1236 | K60: =IS!K25*-1 -> -1297 | L60: =IS!L25*-1 -> -1435 | M60: =M27*M61*-1 -> -1470.875 | N60: =N27*N61*-1 -> -1507.6469 | O60: =O27*O61*-1 -> -1545.338 | P60: =P27*P61*-1 -> -1583.9715 | Q60: =Q27*Q61*-1 -> -1623.5708 | R60: =R27*R61*-1 -> -1664.1601
C61: % sales | H61: =H60/H27*-1 -> 0.063802006 | I61: =I60/I27*-1 -> 0.05140734 | J61: =J60/J27*-1 -> 0.056034092 | K61: =K60/K27*-1 -> 0.055001908 | L61: =L60/L27*-1 -> 0.059886487 | M61: =L61 -> 0.059886487 | N61: =M61 -> 0.059886487 | O61: =N61 -> 0.059886487 | P61: =O61 -> 0.059886487 | Q61: =P61 -> 0.059886487 | R61: =Q61 -> 0.059886487
C63: Taxable income | H63: =H57+H60 -> 5207 | I63: =I57+I60 -> 7259 | J63: =J57+J60 -> 8616 | K63: =K57+K60 -> 9543 | L63: =L57+L60 -> 9528 | M63: =M57+M60 -> 9995.9188 | N63: =N57+N60 -> 10429.471 | O63: =O57+O60 -> 10837.244 | ... R63: =R57+R60 -> 12750.516
C64: % margin | H64: =H63/H$27 -> 0.30903911 | I64: =I63/I$27 -> 0.36947117 | J64: =J63/J$27 -> 0.39060658 | K64: =K63/K$27 -> 0.40469022 | L64: =L63/L$27 -> 0.39762958 | M64: =M63/M$27 -> 0.40698255 | N64: =N63/N$27 -> 0.41427765 | O64: =O63/O$27 -> 0.41997574 | ... R64: =R63/R$27 -> 0.45884024
C66: Taxes | H66: =IS!H33*-1 -> -1237 | I66: =IS!I33*-1 -> -1339 | J66: =IS!J33*-1 -> -1568 | K66: =IS!K33*-1 -> -1899 | L66: =IS!L33*-1 -> -1961 | M66: =M63*M67*-1 -> -2016.8185 | N66: =N63*N67*-1 -> -2104.2939 | O66: =O63*O67*-1 -> -2186.5678 | P66: =P63*P67*-1 -> -2258.1313 | Q66: =Q63*Q67*-1 -> -2465.956 | R66: =R63*R67*-1 -> -2572.5975
C67: % tax rate | H67: =H66/H63*-1 -> 0.23756482 | I67: =I66/I63*-1 -> 0.18446067 | J67: =J66/J63*-1 -> 0.181987 | K67: =K66/K63*-1 -> 0.19899403 | L67: =L66/L63*-1 -> 0.20581444 | M67: =AVERAGE(H67:L67) -> 0.20176419 | N67: =M67 -> 0.20176419 | O67: =N67 -> 0.20176419 | P67: =O67 -> 0.20176419 | Q67: =P67 -> 0.20176419 | R67: =Q67 -> 0.20176419
C69: Net income | H69: =H63+H66 -> 3970 | I69: =I63+I66 -> 5920 | J69: =J63+J66 -> 7048 | K69: =K63+K66 -> 7644 | L69: =L63+L66 -> 7567 | M69: =M63+M66 -> 7979.1003 | N69: =N63+N66 -> 8325.1775 | O69: =O63+O66 -> 8650.6764 | ... R69: =R63+R66 -> 10177.918
C70: % margin | H70: =H69/H$27 -> 0.23562229 | I70: =I69/I$27 -> 0.30131827 | J70: =J69/J$27 -> 0.31952126 | K70: =K69/K$27 -> 0.32415928 | L70: =L69/L$27 -> 0.31579167 | M70: =M69/M$27 -> 0.32486805 | N70: =N69/N$27 -> 0.33069125 | O70: =O69/O$27 -> 0.33523967 | ... R70: =R69/R$27 -> 0.36626271
A72: • | C72: DCF
H74: Actuals | M74: Projections
C75: $M | H75: 2020 | I75: =+H75+1 -> 2021 | J75: =+I75+1 -> 2022 | K75: =+J75+1 -> 2023 | L75: =+K75+1 -> 2024 | M75: =+L75+1 -> 2025 | N75: =+M75+1 -> 2026 | O75: =+N75+1 -> 2027 | P75: =+O75+1 -> 2028 | ... R75: =+Q75+1 -> 2030
C76: EBIT | M76: =M57 -> 11466.794 | N76: =N57 -> 11937.118 | O76: =O57 -> 12382.582 | P76: =P57 -> 12775.905 | Q76: =Q57 -> 13845.541 | R76: =R57 -> 14414.676
C77: (1-Tax) | M77: =(1-M67) -> 0.79823581 | N77: =(1-N67) -> 0.79823581 | O77: =(1-O67) -> 0.79823581 | P77: =(1-P67) -> 0.79823581 | Q77: =(1-Q67) -> 0.79823581 | R77: =(1-R67) -> 0.79823581
C78: EBIAT (or NOPAT) | M78: =M76*M77 -> 9153.2054 | N78: =N76*N77 -> 9528.6352 | O78: =O76*O77 -> 9884.2206 | P78: =P76*P77 -> 10198.185 | Q78: =Q76*Q77 -> 11052.007 | R78: =R76*R77 -> 11506.31
C79: Plus D&A | M79: =-M51 -> 2005.5706 | N79: =-N51 -> 2029.8478 | O79: =-O51 -> 2103.827 | P79: =-P51 -> 2051.1496 | Q79: =-Q51 -> 1800.6914 | R79: =-R51 -> 1770.1186
C80: Less Capex | M80: =-'Estimates IS'!H25 -> -2707 | N80: =-'Estimates IS'!I25 -> -2928 | O80: =-'Estimates IS'!J25 -> -3261 | P80: =-'Estimates IS'!K25 -> -3525 | Q80: =-'Estimates IS'!L25 -> -3774.0819 | R80: =-'Estimates IS'!M25 -> -4040.7644
C81: Less Change in WC | M81: =-M113 -> 2.2585344 | N81: =-N113 -> -56.977664 | O81: =-O113 -> -55.284692 | P81: =-P113 -> -57.367409 | Q81: =-Q113 -> -59.526891 | R81: =-R113 -> -61.765927
C82: Free Cash Flow | M82: =SUM(M78:M81) -> 8454.0345 | N82: =SUM(N78:N81) -> 8573.5054 | O82: =SUM(O78:O81) -> 8671.7629 | P82: =SUM(P78:P81) -> 8666.9667 | Q82: =SUM(Q78:Q81) -> 9019.0895 | R82: =SUM(R78:R81) -> 9173.8987
C84: Discount period not corrected | M84: 1 | N84: =M84+1 -> 2 | O84: =N84+1 -> 3 | P84: =O84+1 -> 4 | Q84: =P84+1 -> 5 | R84: =Q84+1 -> 6
C85: Fraction of year left | M85: =1-(9/12) -> 0.25 | N85: =M85+1 -> 1.25 | O85: =N85+1 -> 2.25 | P85: =O85+1 -> 3.25 | Q85: =P85+1 -> 4.25 | R85: =Q85+1 -> 5.25
C86: Mid year convention DP | M86: =M85*0.5 -> 0.125 | N86: =M85+0.5 -> 0.75 | O86: =N86+1 -> 1.75 | P86: =O86+1 -> 2.75 | Q86: =P86+1 -> 3.75 | R86: =Q86+1 -> 4.75
C88: Discounted FCF | M88: =M82/(1+wacc)^M86 -> 8391.3916 | N88: =N82/(1+wacc)^N86 -> 8199.328 | O88: =O82/(1+wacc)^O86 -> 7814.2449 | P88: =P82/(1+wacc)^P86 -> 7358.7921 | Q88: =Q82/(1+wacc)^Q86 -> 7215.4244 | R88: =R82/(1+wacc)^R86 -> 6915.33
C90: Terminal value | R90: =(R82*(1+Tgr))/(wacc-Tgr) -> 259006.79
C91: Discounted TV | R91: =R90/(1+wacc)^R86 -> 195240.6
C93: Enterprise value | R93: =R91+SUM(M88:R88) -> 241135.11
C94: Plus Cash | R94: =BS!L10 -> 1047.803
C95: Less Debt | R95: =-D -> -49552.872
C96: Equity value | R96: =SUM(R93:R95) -> 192630.04
C97: Number of shares | R97: =IS!M48 -> 712.1
C98: Price per share | R98: =R96/R97 -> 270.50981
A100: • | C100: Working Cap
C102: AR | H102: =BS!H12 -> 1724.7354 | I102: =BS!I12 -> 1646.5002 | J102: =BS!J12 -> 1981.7287 | K102: =BS!K12 -> 2252.2972 | L102: =BS!L12 -> 2301.3037 | M102: =M27*M103 -> 2296.768 | N102: =N27*N103 -> 2354.1872 | O102: =O27*O103 -> 2413.0419 | P102: =P27*P103 -> 2473.3679 | Q102: =Q27*Q103 -> 2535.2021 | R102: =R27*R103 -> 2598.5822
C103: % sales | H103: =H102/H$27 -> 0.10236426 | I103: =I102/I$27 -> 0.083804153 | J103: =J102/J$27 -> 0.089841723 | K103: =K102/K$27 -> 0.095513217 | L103: =L102/L$27 -> 0.096039715 | M103: =AVERAGE(H103:L103) -> 0.093512614 | N103: =M103 -> 0.093512614 | O103: =N103 -> 0.093512614 | P103: =O103 -> 0.093512614 | Q103: =P103 -> 0.093512614 | R103: =Q103 -> 0.093512614
C104: inventories | H104: =BS!H15 -> 41.76372 | I104: =BS!I15 -> 48.892016 | J104: =BS!J15 -> 48.723354 | K104: =BS!K15 -> 47.797947 | L104: =BS!L15 -> 54.080153 | M104: =M27*M105 -> 56.293856 | N104: =N27*N105 -> 57.701203 | O104: =O27*O105 -> 59.143733 | P104: =P27*P105 -> 60.622326 | Q104: =Q27*Q105 -> 62.137884 | R104: =R27*R105 -> 63.691331
C105: % sales | H105: =H104/H$27 -> 0.0024787062 | I105: =I104/I$27 -> 0.0024885232 | J105: =J104/J$27 -> 0.0022088745 | K105: =K104/K$27 -> 0.0020269686 | L105: =L104/L$27 -> 0.0022569132 | M105: =AVERAGE(H105:L105) -> 0.0022919971 | N105: =M105 -> 0.0022919971 | O105: =N105 -> 0.0022919971 | P105: =O105 -> 0.0022919971 | Q105: =P105 -> 0.0022919971 | R105: =Q105 -> 0.0022919971
C106: Tot current assets | H106: =H104+H102 -> 1766.4991 | I106: =I104+I102 -> 1695.3922 | J106: =J104+J102 -> 2030.4521 | K106: =K104+K102 -> 2300.0951 | L106: =L104+L102 -> 2355.3838 | M106: =M104+M102 -> 2353.0618 | N106: =N104+N102 -> 2411.8884 | O106: =O104+O102 -> 2472.1856 | ... R106: =R104+R102 -> 2662.2735
C108: AP | H108: =BS!H41 -> 605.86 | I108: =BS!I41 -> 885.33241 | J108: =BS!J41 -> 918.43522 | K108: =BS!K41 -> 998.41582 | L108: =BS!L41 -> 993.72281 | M108: =M33*M109*-1 -> 993.65937 | N108: =N33*N109*-1 -> 995.50826 | O108: =O33*O109*-1 -> 1000.5208 | P108: =P33*P109*-1 -> 1004.958 | Q108: =Q33*Q109*-1 -> 1008.7809 | R108: =R33*R109*-1 -> 1011.9484
C109: % COGS | H109: =H108/H33*-1 -> 0.089254567 | I109: =I108/I33*-1 -> 0.11832831 | J109: =J108/J33*-1 -> 0.11728199 | K109: =K108/K33*-1 -> 0.11859079 | L109: =L108/L33*-1 -> 0.11656573 | M109: =L109 -> 0.11656573 | N109: =M109 -> 0.11656573 | O109: =N109 -> 0.11656573 | P109: =O109 -> 0.11656573 | Q109: =P109 -> 0.11656573 | R109: =Q109 -> 0.11656573
C110: Tot current liab | H110: =H108 -> 605.86 | I110: =I108 -> 885.33241 | J110: =J108 -> 918.43522 | K110: =K108 -> 998.41582 | L110: =L108 -> 993.72281 | M110: =M108 -> 993.65937 | N110: =N108 -> 995.50826 | O110: =O108 -> 1000.5208 | ... R110: =R108 -> 1011.9484
C112: WC | H112: =H106-H110 -> 1160.6391 | I112: =I106-I110 -> 810.05981 | J112: =J106-J110 -> 1112.0169 | K112: =K106-K110 -> 1301.6793 | L112: =L106-L110 -> 1361.661 | M112: =M106-M110 -> 1359.4025 | N112: =N106-N110 -> 1416.3801 | O112: =O106-O110 -> 1471.6648 | ... R112: =R106-R110 -> 1650.325
C113: Change in WC | I113: =I112-H112 -> -350.57932 | J113: =J112-I112 -> 301.95705 | K113: =K112-J112 -> 189.66245 | L113: =L112-K112 -> 59.981689 | M113: =M112-L112 -> -2.2585344 | N113: =N112-M112 -> 56.977664 | O113: =O112-N112 -> 55.284692 | P113: =P112-O112 -> 57.367409 | ... R113: =R112-Q112 -> 61.765927
A115: • | C115: End

Sheet INPUT>>

Sheet WACC
C3: WACC
C5: WACC = kE*(E/E+D) + kd * D/D+E * (1-tax)
C6: Ke = Rf + Beta * (Rm - Rf)
C7: Rm - Rf = MRP
C9: Rf | D9: 0.0438 | F9: 10-yr treas yield - google
C10: Beta | D10: 0.57 | F10: Factset
C11: MRP | D11: 0.046 | F11: Damodoran
C12: Ke | D12: =D9+D10*D11 -> 0.07002
C14: E | D14: 217140 | F14: Factset
C15: D | D15: =BS!L48 -> 49552.872 | F15: BS
C16: E% | D16: =E/(SUM(D14:D15)) -> 0.81419499
C17: D% | D17: =D/SUM(D14:D15) -> 0.18580501
C18: 1-Tax | D18: =(1-'DCF model'!M67) -> 0.79823581
C19: Kd | D19: =IS!L25/D -> 0.028958968
C21: WACC | D21: =ke*E_perc+kd*Tax_shield*D_perc -> 0.061305018

Sheet Estimates IS
B1: MCD-US
B2: Income Statement (M)
C3: Dec '20 | D3: Dec '21 | E3: Dec '22 | F3: Dec '23 | G3: Dec '24 | H3: Dec '25E | I3: Dec '26E | J3: Dec '27E | K3: Dec '28E | L3: Dec '29E | M3: Dec '30E
B4: Sales | C4: 15845 | D4: 20830 | E4: 21346 | F4: 23769 | G4: 25127 | H4: 23060 | I4: 24346 | J4: 25549 | K4: 26280 | L4: 26724 | M4: 27928
B5: Cost of Sales | C5: 5759 | D5: 7218 | E5: 6796 | F5: 7668 | G5: 8079 | H5: 7100 | I5: 7503 | J5: 7846 | K5: - | L5: - | M5: -
B6: Gross Income | C6: - | D6: 10463 | E6: 11493 | F6: 13578 | G6: - | H6: 12019 | I6: 12871 | J6: - | K6: - | L6: - | M6: -
B7: Compensation and Benefits | C7: - | D7: - | E7: - | F7: - | G7: - | H7: 2212 | I7: 2328 | J7: - | K7: - | L7: - | M7: -
B8: EBITDA | C8: 7314 | D8: 10722 | E8: 11281 | F8: 12964 | G8: 13602 | H8: 12649 | I8: 13507 | J8: 14343 | K8: 14732 | L8: 15423 | M8: 16266
B9: Operating Income | C9: 5890 | D9: 9158 | E9: 9558 | F9: 11114 | G9: 11634 | H9: 10766 | I9: 11544 | J9: 12260 | K9: 12694 | L9: 13648 | M9: 14487
B10: Pretax Income | C10: 4926 | D10: 7998 | E10: 8595 | F10: 9820 | G10: 10258 | H10: 9456 | I10: 10235 | J10: 10972 | K10: 11366 | L10: 12298 | M10: 13128
B11: Tax Expense | C11: 1163 | D11: 1609 | E11: 1517 | F11: 1915 | G11: 2056 | H11: 2020 | I11: 2158 | J11: 2327 | K11: 2418 | L11: 2582 | M11: 2757
B12: Net Income | C12: 3744 | D12: 6258 | E12: 6892 | F12: 8151 | G12: 8200 | H12: 7465 | I12: 8083 | J12: 8675 | K12: 8988 | L12: 9813 | M12: 10466
B14: % margin EBITDA | H14: =H8/H4 -> 0.54852559 | I14: =I8/I4 -> 0.5547934 | J14: =J8/J4 -> 0.56139184 | K14: =K8/K4 -> 0.56057839 | L14: =L8/L4 -> 0.57712169 | M14: =M8/M4 -> 0.58242624
H15: =H8-H6 -> 630 | I15: =I8-I6 -> 636 | J15: =J8-J6 -> #VALUE! | K15: =K8-K6 -> #VALUE! | L15: =L8-L6 -> #VALUE! | M15: =M8-M6 -> #VALUE!
H17: =H8-H9 -> 1883 | I17: =I8-I9 -> 1963 | J17: =J8-J9 -> 2083 | K17: =K8-K9 -> 2038 | L17: =L8-L9 -> 1775 | M17: =M8-M9 -> 1779
H18: =H17/H4 -> 0.081656548 | I18: =I17/I4 -> 0.080629261 | J18: =J17/J4 -> 0.08152961 | K18: =K17/K4 -> 0.077549467 | L18: =L17/L4 -> 0.066419698 | M18: =M17/M4 -> 0.063699513
H20: =H12/H4 -> 0.32372073 | I20: =I12/I4 -> 0.33200526 | J20: =J12/J4 -> 0.33954362 | K20: =K12/K4 -> 0.34200913 | L20: =L12/L4 -> 0.36719802 | M20: =M12/M4 -> 0.37474936
B25: Capex | C25: 1354 | D25: 1830 | E25: 1749 | F25: 2198 | G25: 2690 | H25: 2707 | I25: 2928 | J25: 3261 | K25: 3525 | L25: =K25*(1+L27) -> 3774.0819 | M25: =L25*(1+M27) -> 4040.7644
B26: % sales | C26: =C25/C4 -> 0.085452824 | D26: =D25/D4 -> 0.087854057 | E26: =E25/E4 -> 0.081935726 | F26: =F25/F4 -> 0.09247339 | G26: =G25/G4 -> 0.10705615 | H26: =H25/H4 -> 0.11738942 | I26: =I25/I4 -> 0.12026616 | J26: =J25/J4 -> 0.12763709 | K26: =K25/K4 -> 0.13413242
B27: % growth | D27: =D25/C25-1 -> 0.35155096 | E27: =E25/D25-1 -> -0.044262295 | F27: =F25/E25-1 -> 0.25671812 | G27: =G25/F25-1 -> 0.22383985 | H27: =H25/G25-1 -> 0.0063197026 | I27: =I25/H25-1 -> 0.081640192 | J27: =J25/I25-1 -> 0.11372951 | K27: =K25/J25-1 -> 0.080956762 | L27: =AVERAGE(H27:K27) -> 0.070661541 | M27: =L27 -> 0.070661541

Sheet IS
B1: McDonald's Corporation (MCD)
B2: $310.45
B5: McDonald's Corporation
B6: MCD 580135101 2550707 NYSE Common stock
B7: Source: FactSet Fundamentals
C8: DEC '15 | D8: DEC '16 | E8: DEC '17 | F8: DEC '18 | G8: DEC '19 | H8: DEC '20 | I8: DEC '21 | J8: DEC '22 | K8: DEC '23 | L8: DEC '24 | M8: SEP '25 | O8: fractin of the year recorded
M9: LTM | O9: calculate with a prop the total of the year
G10: Restate
B11: Sales | C11: 22917 | D11: 22258 | E11: 20232 | F11: 17822 | G11: 19088 | H11: 16849 | I11: 19647 | J11: 22058 | K11: 23581 | L11: 23962 | M11: 23790 | O11: =9/12 -> 0.75
B12: Cost of Goods Sold (COGS) incl. D&A | C12: 14089 | D12: 13033 | E12: 10816 | F12: 8679 | G12: 9134 | H12: 8324 | I12: 9063 | J12: 9611 | K12: 10249 | L12: 10463 | M12: 10171 | O12: =M11/O11 -> 31720
B13: COGS excluding D&A | C13: 12686 | D13: 11662 | E13: 9607 | F13: 7423 | G13: 7689 | H13: 6788 | I13: 7482 | J13: 7831 | K13: 8419 | L13: 8525 | M13: 8200
B14: Depreciation & Amortization Expense | C14: 1403 | D14: 1371 | E14: 1209 | F14: 1256 | G14: 1446 | H14: 1536 | I14: 1580 | J14: 1780 | K14: 1830 | L14: 1939 | M14: 1971
B15: Depreciation | C15: 1297 | D15: 1257 | E15: 1088 | F15: 1104 | G15: 1244 | H15: 1289 | I15: 1295 | J15: 1383 | K15: 1389 | L15: 1387
B16: Amortization of Intangibles | C16: 106 | D16: 114 | E16: 120 | F16: 152 | G16: 202 | H16: 247 | I16: 285 | J16: 396 | K16: 441 | L16: 552
B17: Gross Income | C17: 8828 | D17: 9225 | E17: 9416 | F17: 9143 | G17: 9954 | H17: 8525 | I17: 10585 | J17: 12447 | K17: 13332 | L17: 13499 | M17: 13619
B18: SG&A Expense | C18: 2195 | D18: 2156 | E18: 1978 | F18: 1865 | G18: 2021 | H18: 2243 | I18: 2316 | J18: 2595 | K18: 2492 | L18: 2535 | M18: 2640
B19: Other SG&A | C19: 2195 | D19: 2156 | E19: 1978 | F19: 1865 | G19: 2021 | H19: 2243 | I19: 2316 | J19: 2595 | K19: 2492 | L19: 2535 | M19: 2640
B20: EBIT (Operating Income) | C20: 6632 | D20: 7069 | E20: 7438 | F20: 7278 | G20: 7932 | H20: 6283 | I20: 8269 | J20: 9852 | K20: 10840 | L20: 10964 | M20: 10978
B21: Nonoperating Income - Net | C21: -2 | D21: 218 | E21: 296 | F21: 356 | G21: 267 | H21: -82 | I21: 118 | J21: -1263 | K21: 861 | L21: 272 | M21: 2168
B22: Nonoperating Interest Income | C22: 9 | D22: 4 | E22: 6 | F22: 3 | G22: 33 | H22: 16 | I22: 8 | J22: 42 | K22: 172 | L22: 95 | M22: 73
B23: Equity in Earnings of Affiliates | C23: -132 | D23: 50 | E23: 163 | F23: 128 | G23: 137 | H23: 103 | I23: 149 | J23: 108 | K23: 142 | L23: 145 | M23: 176
B24: Other Income (Expense) | C24: 121 | D24: 165 | E24: 127 | F24: 224 | G24: 97 | H24: -201 | I24: -39 | J24: -1413 | K24: 547 | L24: 31 | M24: 1919
B25: Interest Expense | C25: 575 | D25: 799 | E25: 816 | F25: 831 | G25: 1057 | H25: 1075 | I25: 1010 | J25: 1236 | K25: 1297 | L25: 1435 | M25: 1460
B26: Gross Interest Expense | C26: 584 | D26: 806 | E26: 821 | F26: 835 | G26: 1063 | H26: 1080 | I26: 1016 | J26: 1245 | K26: 1303 | L26: 1443 | M26: 1460
B27: Interest Capitalized | C27: 8 | D27: 6 | E27: 5 | F27: 5 | G27: 7 | H27: 5 | I27: 6 | J27: 9 | K27: 6 | L27: 8
B28: Unusual Expense - Net | C28: 143 | D28: 281 | E28: -684 | F28: 177 | G28: -21 | H28: -261 | I28: -346 | J28: -94 | K28: 671 | L28: 238 | M28: 2015
B29: Restructuring Expense | C29: 212 | D29: 309 | E29: -623 | F29: 196 | G29: 66 | H29: -235 | I29: -241 | J29: 961 | K29: 335 | L29: 268 | M29: 138
B30: Unrealized Valuation Gain/Loss | C30: 69 | D30: 27 | E30: 61 | F30: 19 | G30: 87 | H30: 26 | I30: 104 | J30: 1055 | K30: -336 | L30: 31 | M30: -1878
B31: Hedges/Derivatives | C31: 69 | D31: 27 | E31: 61 | F31: 19 | G31: 87 | H31: 26 | I31: 104 | J31: 1055 | K31: -336 | L31: 31 | M31: -1878
B32: Pretax Income | C32: 5912 | D32: 6207 | E32: 7601 | F32: 6625 | G32: 7164 | H32: 5387 | I32: 7723 | J32: 7446 | K32: 9733 | L32: 9564 | M32: 9671
B33: Income Taxes | C33: 1827 | D33: 1970 | E33: 2998 | F33: 1604 | G33: 1780 | H33: 1237 | I33: 1339 | J33: 1568 | K33: 1899 | L33: 1961 | M33: 2048
B34: Income Taxes - Current Domestic | C34: 1093 | D34: 1056 | E34: 1951 | F34: 404 | G34: 640 | H34: 591 | I34: 944 | J34: 727 | K34: 1482 | L34: 1554
B35: Income Taxes - Current Foreign | C35: 736 | D35: 1401 | E35: 1079 | F35: 1112 | G35: 1006 | H35: 641 | I35: 757 | J35: 1170 | K35: 1052 | L35: 937
B36: Income Taxes - Deferred Domestic | C36: 3 | D36: -98 | E36: -95 | F36: 139 | G36: 52 | H36: 828 | I36: -170 | J36: -120 | K36: -162 | L36: -89
B37: Income Taxes - Deferred Foreign | C37: -4 | D37: -389 | E37: 63 | F37: -52 | G37: 81 | H37: -822 | I37: -192 | J37: -209 | K37: -472 | L37: -442
B38: Consolidated Net Income | C38: 4084 | D38: 4237 | E38: 4603 | F38: 5022 | G38: 5383 | H38: 4150 | I38: 6384 | J38: 5878 | K38: 7833 | L38: 7602 | M38: 7623
B39: Net Income | C39: 4084 | D39: 4237 | E39: 4603 | F39: 5022 | G39: 5383 | H39: 4150 | I39: 6384 | J39: 5878 | K39: 7833 | L39: 7602 | M39: 7623
B40: Net Income available to Common | C40: 4084 | D40: 4237 | E40: 4603 | F40: 5022 | G40: 5383 | H40: 4150 | I40: 6384 | J40: 5878 | K40: 7833 | L40: 7602 | M40: 7623
B41: Per Share
B42: EPS (recurring) | C42: 4.43 | D42: 5.15 | E42: 5.06 | F42: 6.55 | G42: 7.02 | H42: 5.29 | I42: 8.17 | J42: 7.84 | K42: 11.34 | L42: 10.76 | M42: 12.62
B43: EPS (basic) | C43: 4.35 | D43: 4.96 | E43: 5.7 | F43: 6.45 | G43: 7.1 | H43: 5.57 | I43: 8.55 | J43: 7.98 | K43: 10.76 | L43: 10.58 | M43: 10.67
B44: Basic Shares Outstanding | C44: 939.4 | D44: 854.4 | E44: 807.4 | F44: 778.2 | G44: 758.1 | H44: 744.6 | I44: 746.3 | J44: 736.5 | K44: 727.9 | L44: 718.3 | M44: 712.9
B45: Total Shares Outstanding | C45: 906.8 | D45: 819.3 | E45: 794.1 | F45: 767.1 | G45: 746.3 | H45: 745.4 | I45: 745.4 | J45: 744.8 | K45: 731.3 | L45: 715.2 | M45: 712.1
B46: EPS (diluted) | C46: 4.33 | D46: 4.92 | E46: 5.65 | F46: 6.39 | G46: 7.04 | H46: 5.53 | I46: 8.49 | J46: 7.93 | K46: 10.7 | L46: 10.53 | M46: 10.62
B47: Diluted Shares Outstanding | C47: 944.6 | D47: 861.2 | E47: 815.5 | F47: 785.6 | G47: 764.9 | H47: 750.1 | I47: 751.8 | J47: 741.3 | K47: 732.3 | L47: 721.9 | M47: 715.9
B48: Total Shares Outstanding | C48: 906.8 | D48: 819.3 | E48: 794.1 | F48: 767.1 | G48: 746.3 | H48: 745.4 | I48: 745.4 | J48: 744.8 | K48: 731.3 | L48: 715.2 | M48: 712.1
B49: Earnings Persistence | C49: 88.03 | D49: 91.89 | E49: 88.7 | F49: 90.97 | G49: 75.15 | H49: 92.54 | I49: 95.26 | J49: 93.07 | K49: 86.94 | L49: 85.76
B50: Dividends per Share | C50: 3.1 | D50: 3.26 | E50: 3.4 | F50: 3.55 | G50: 4.23 | H50: 4.42 | I50: 4.44 | J50: 5.39 | K50: 5.76 | L50: 6.27 | M50: 6.41
B51: Payout Ratio | C51: 71.67 | D51: 66.36 | E51: 60.13 | F51: 55.57 | G51: 60.05 | H51: 79.92 | I51: 52.31 | J51: 67.92 | K51: 53.87 | L51: 59.52 | M51: 60.38
B52: EBITDA
B53: EBITDA | C53: 8035 | D53: 8440 | E53: 8647 | F53: 8534 | G53: 9378 | H53: 7819 | I53: 9849 | J53: 11632 | K53: 12669 | L53: 12903 | M53: 12949
B54: EBIT | C54: 6632 | D54: 7069 | E54: 7438 | F54: 7278 | G54: 7932 | H54: 6283 | I54: 8269 | J54: 9852 | K54: 10840 | L54: 10964 | M54: 10978
B55: Depreciation & Amortization Expense | C55: 1403 | D55: 1371 | E55: 1209 | F55: 1256 | G55: 1446 | H55: 1536 | I55: 1580 | J55: 1780 | K55: 1830 | L55: 1939 | M55: 1971
B56: All figures in millions of Euro except per share items.

Sheet BS
B4: McDonald's Corporation
B5: MCD 580135101 2550707 NYSE Common stock
B6: Source: FactSet Fundamentals
C7: DEC '15 | D7: DEC '16 | E7: DEC '17 | F7: DEC '18 | G7: DEC '19 | H7: DEC '20 | I7: DEC '21 | J7: DEC '22 | K7: DEC '23 | L7: DEC '24
G8: Restate
B9: Assets
B10: Cash & Short-Term Investments | C10: 7074.9332 | D10: 1159.8957 | E10: 2051.7988 | F10: 757.55587 | G10: 800.44544 | H10: 2818.9285 | I10: 4141.0482 | J10: 2420.9885 | K10: 4145.4761 | L10: 1047.803
B11: Cash Only | C11: 7074.9332 | D11: 1159.8957 | E11: 2051.7988 | F11: 757.55587 | G11: 800.44544 | H11: 2818.9285 | I11: 4141.0482 | J11: 2420.9885 | K11: 4145.4761 | L11: 1047.803
B12: Short-Term Receivables | C12: 1195.5261 | D12: 1397.5824 | E12: 1645.7362 | F12: 2135.7652 | G12: 1981.4699 | H12: 1724.7354 | I12: 1646.5002 | J12: 1981.7287 | K12: 2252.2972 | L12: 2301.3037
B13: Accounts Receivables, Net | C13: 1195.5261 | D13: 1397.5824 | E13: 1645.7362 | F13: 2135.7652 | G13: 1981.4699 | H13: 1724.7354 | I13: 1646.5002 | J13: 1981.7287 | K13: 2252.2972 | L13: 2301.3037
B14: Accounts Receivables, Gross | C14: 1195.5261 | D14: 1397.5824 | E14: 1645.7362 | F14: 2135.7652 | G14: 1981.4699 | H14: 1724.7354 | I14: 1646.5002 | J14: 1981.7287 | K14: 2252.2972 | L14: 2301.3037
B15: Inventories | C15: 92.147656 | D15: 55.842618 | E15: 48.967356 | F15: 44.701045 | G15: 44.721604 | H15: 41.76372 | I15: 48.892016 | J15: 48.723354 | K15: 47.797947 | L15: 54.080153
B16: Finished Goods | C16: 92.147656 | D16: 55.842618 | E16: 48.967356 | F16: 44.701045 | G16: 44.721604 | H16: 41.76372 | I16: 48.892016 | J16: 48.723354
B17: Other Current Assets | C17: 514.31464 | D17: 1983.598 | E17: 689.87342 | F17: 607.61929 | G17: 342.98441 | H17: 517.10188 | I17: 449.61309 | J17: 630.96744 | K17: 784.23032 | L17: 1037.1801
B18: Miscellaneous Current Assets | C18: 514.31464 | D18: 1983.598 | E18: 689.87342 | F18: 607.61929 | G18: 342.98441 | H18: 517.10188 | I18: 449.61309 | J18: 630.96744 | K18: 784.23032 | L18: 1037.1801
B19: Total Current Assets | C19: 8876.9216 | D19: 4596.9188 | E19: 4436.3758 | F19: 3545.6414 | G19: 3169.6214 | H19: 5102.5295 | I19: 6286.0535 | J19: 5082.408 | K19: 7229.8015 | L19: 4440.3668
B20: Net Property, Plant & Equipment | C20: 21281.046 | D20: 20154.16 | E20: 18694.454 | F20: 19982.242 | G20: 33337.372 | H20: 31699.481 | I20: 33655.118 | J20: 34049.473 | K20: 34782.059 | L20: 37309.511
B21: Property, Plant & Equipment - Gross | C21: 34697.965 | D21: 32655.511 | E21: 30501.666 | F21: 32536.062 | G21: 46603.208 | H21: 45199.788 | I21: 48776.469 | J21: 50225.626 | K21: 51676.46 | L21: 55544.18
B22: Buildings | C22: 24767.191 | D22: 23898.649 | E22: 22723.268 | F22: 24704.544 | G22: 26378.263 | H22: 25812.921 | I22: 28094.707 | J22: 29445.959 | K22: 30219.165 | L22: 32741.67
B23: Land & Improvements | C23: 5139.0039 | D23: 5181.3227 | E23: 4715.3565 | F23: 4829.9873 | G23: 5368.7306 | H23: 5189.081 | I23: 5704.8893 | J23: 6264.98 | K23: 6410.4469 | L23: 7004.3455
B24: Machinery & Equipment | C24: 4288.4102 | D24: 3101.1141 | E24: 2636.3258 | F24: 2574.1153 | G24: 2667.706 | H24: 2549.1398 | I24: 2666.1977 | J24: 2341.1572 | K24: 2437.6047 | L24: 2497.3442
B25: Other Property, Plant & Equipment | C25: 503.36003 | D25: 474.42523 | E25: 426.71553 | F25: 427.41547 | G25: 374.52116 | H25: 347.34992 | I25: 393.68625 | J25: 399.6252 | K25: 375.14146 | L25: 419.12119
B26: Operating Lease Right-of-Use Assets | G26: 11813.987 | H26: 11301.295 | I26: 11916.989 | J26: 11773.905 | K26: 12234.102 | L26: 12881.699
B27: Accumulated Depreciation | C27: 13416.92 | D27: 12501.351 | E27: 11807.212 | F27: 12553.82 | G27: 13265.835 | H27: 13500.307 | I27: 15121.351 | J27: 16176.154 | K27: 16894.401 | L27: 18234.669
B28: Total Long-Term Investments | C28: 863.94181 | D28: 692.20196 | E28: 1043.5543 | F28: 1055.5045 | G28: 1310.4677 | H28: 1089.4528 | I28: 1264.5973 | J28: 1024.3148 | K28: 1150.7718 | L28: 2655.7218
B29: LT Investment - Affiliate Companies | C29: 729.72475 | D29: 688.21997 | E29: 904.14724 | F29: 1052.1804 | G29: 1131.6704 | H29: 1060.1937 | I29: 1056.2786 | J29: 997.42328 | K29: 977.86632 | L29: 2617.0931
B30: Other Long-Term Investments | C30: 134.21707 | D30: 3.981986 | E30: 139.40706 | F30: 3.324148 | G30: 178.79733 | H30: 29.259123 | I30: 208.31868 | J30: 26.891544 | K30: 172.90545 | L30: 38.628681
B31: Intangible Assets | C31: 2316.3951 | D31: 2215.2169 | E31: 1981.7622 | F31: 2039.5398 | G31: 2977.9956 | H31: 2831.3514 | I31: 3145.8847 | J31: 3527.4771 | K31: 3509.1659 | L31: 3913.0854
B32: Goodwill | C32: 2316.3951 | D32: 2215.2169 | E32: 1981.7622 | F32: 2039.5398 | G32: 2385.2116 | H32: 2266.4378 | I32: 2446.7992 | J32: 2717.6388 | K32: 2752.3651 | L32: 3037.18
B33: Other Intangible Assets | C33: 0 | D33: 0 | E33: 0 | F33: 0 | G33: 592.78397 | H33: 564.91357 | I33: 699.08548 | J33: 809.83836 | K33: 756.80082 | L33: 875.90534
B34: Deferred Tax Assets | C34: 490.47224 | D34: 762.26595 | E34: 722.76816 | F34: 1066.7016 | G34: 1014.6103 | H34: 1745.4947 | I34: 2072.6346 | J34: 2320.9182 | K34: 2736.523 | L34: 3421.5354
B35: Other Assets | C35: 1095.9219 | D35: 992.74712 | E35: 1272.0686 | F35: 1012.8155 | G35: 515.81292 | H35: 543.25528 | I35: 932.64159 | J35: 1252.9398 | K35: 1419.3636 | L35: 1549.9758
B36: Tangible Other Assets | C36: 1095.9219 | D36: 992.74712 | E36: 1272.0686 | F36: 1012.8155 | G36: 515.81292 | H36: 543.25528 | I36: 932.64159 | J36: 1252.9398 | K36: 1419.3636 | L36: 1549.9758
B37: Total Assets | C37: 34924.698 | D37: 29413.511 | E37: 28150.983 | F37: 28702.445 | G37: 42325.88 | H37: 43011.565 | I37: 47356.93 | J37: 47257.531 | K37: 50827.685 | L37: 53290.196
B38: Liabilities & Shareholders' Equity
B39: Current
B40: ST Debt & Curr. Portion LT Debt | C40: 0 | D40: 73.192701 | E40: 0 | F40: 0 | G40: 605.87974 | H40: 2407.0124 | I40: 620.38341 | J40: 619.44249 | K40: 2607.6134 | L40: 614.19602
B41: Accounts Payable | C41: 805.21034 | D41: 716.75754 | E41: 770.15324 | F41: 1056.6417 | G41: 880.35636 | H41: 605.86 | I41: 885.33241 | J41: 918.43522 | K41: 998.41582 | L41: 993.72281
B42: Income Tax Payable | C42: 142.50207 | D42: 253.33018 | E42: 221.35243 | F42: 199.71132 | G42: 295.50112 | H42: 605.69654 | I42: 317.18256 | J42: 257.57788 | K42: 638.30174 | L42: 348.62384
B43: Other Current Liabilities | C43: 1768.296 | D43: 2244.987 | E43: 1415.7229 | F43: 1344.7929 | G43: 1444.098 | H43: 1433.2884 | I43: 1712.0999 | J43: 1767.0649 | K43: 1964.8758 | L43: 1772.0907
B44: Accrued Payroll | C44: 1243.4871 | D44: 1095.4255 | E44: 923.05131 | F44: 859.99212 | G44: 913.67484 | H44: 862.89894 | I44: 1181.5864 | J44: 1141.1572 | K44: 1256.4161 | L44: 1083.5345
B45: Miscellaneous Current Liabilities | C45: 524.80898 | D45: 1149.5615 | E45: 492.67156 | F45: 484.80076 | G45: 530.42317 | H45: 570.38944 | I45: 530.51355 | J45: 625.9077 | K45: 708.45971 | L45: 688.55623
B46: Total Current Liabilities | C46: 2716.0084 | D46: 3288.2674 | E46: 2407.2285 | F46: 2601.1459 | G46: 3225.8352 | H46: 5051.8573 | I46: 3534.9983 | J46: 3562.5205 | K46: 6209.2067 | L46: 3728.6334
B47: Long-Term
B48: Long-Term Debt | C48: 22205.744 | D48: 24535.198 | E48: 24597.269 | F48: 27183.921 | G48: 41760.268 | H48: 39653.549 | I48: 42774.886 | J48: 45010.916 | K48: 45453.856 | L48: 49552.872
B49: Long-Term Debt excl Lease Obligations | C49: 22205.744 | D49: 24535.198 | E49: 24597.269 | F49: 27183.921 | G49: 30394.744 | H49: 28766.131 | I49: 31324.921 | J49: 33641.134 | K49: 33633.188 | L49: 37106.711
B50: Capital and Operating Lease Obligations | C50: 0 | D50: 0 | E50: 0 | F50: 0 | G50: 11365.523 | H50: 10887.418 | I50: 11449.965 | J50: 11369.782 | K50: 11820.668 | L50: 12446.161
B51: Deferred Tax Liabilities | C51: 1568.9036 | D51: 1722.7779 | E51: 932.21187 | F51: 1063.29 | G51: 1174.2539 | H51: 1655.5106 | I51: 1825.1847 | J51: 1871.6327 | K51: 1521.6585 | L51: 1848.3824
B52: Other Liabilities | C52: 1909.2332 | D52: 1957.1463 | E52: 2935.7928 | F52: 3328.7845 | G52: 3479.8218 | H52: 3045.8911 | I52: 3267.763 | J52: 2437.5732 | K52: 1903.7705 | L52: 1827.1366
B53: Other Liabilities (excl. Deferred Income) | C53: 1909.2332 | D53: 1957.1463 | E53: 2935.7928 | F53: 2779.6002 | G53: 2891.3141 | H53: 2472.1507 | I53: 2618.5368 | J53: 1727.524 | K53: 1188.5213 | L53: 1075.8088
B54: Deferred Income | F54: 549.18426 | G54: 588.5078 | H54: 573.74035 | I54: 649.22618 | J54: 710.04919 | K54: 715.2492 | L54: 751.32784
B55: Total Liabilities | C55: 28399.889 | D55: 31503.39 | E55: 30872.502 | F55: 34177.142 | G55: 49640.179 | H55: 49406.808 | I55: 51402.832 | J55: 52882.642 | K55: 55088.491 | L55: 56957.024
B56: Equity
B57: Common Equity | C57: 6524.8089 | D57: -2089.8792 | E57: -2721.519 | F57: -5474.697 | G57: -7314.2985 | H57: -6395.2434 | I57: -4045.9023 | J57: -5625.1112 | K57: -4260.8067 | L57: -3666.8275
B58: Common Stock Par/Carry Value | C58: 15.28123 | D58: 15.738327 | E58: 13.824117 | F58: 14.521279 | G58: 14.788419 | H58: 13.567079 | I58: 14.597257 | J58: 15.553994 | K58: 15.027385 | L58: 16.417189
B59: Additional Paid-In Capital/Capital Surplus | C59: 6014.3606 | D59: 6407.1108 | E59: 5889.7402 | F59: 6452.3465 | G59: 6818.6192 | H59: 6459.5644 | I59: 7238.4806 | J59: 8008.5265 | K59: 8050.4235 | L59: 8962.8196
B60: Retained Earnings | C60: 41051.735 | D60: 43823.371 | E60: 40244.671 | F60: 44164.807 | G60: 47154.121 | H60: 44058.764 | I60: 50593.3 | J60: 55791.895 | K60: 57466.077 | L60: 64542.731
B61: Cumulative Translation Adjustment/Unrealized For. Exch. Gain | C61: -2513.0258 | D61: -2757.7152 | E61: -1641.9887 | F61: -2121.5938 | G61: -2005.3452 | H61: -1788.1574 | I61: -2083.5385 | J61: -2079.2691 | K61: -1885.6652 | L61: -2200.8691
B62: Other Appropriated Reserves | C62: -137.99135 | D62: -174.63854 | E62: -172.13524 | F62: -161.13371 | G62: -206.41426 | H62: -326.01855 | I62: -179.65178 | J62: -250.64418 | K62: -337.66352 | L62: -264.60646
B63: Treasury Stock | C63: -37905.551 | D63: -49403.746 | E63: -47055.63 | F63: -53823.644 | G63: -59090.067 | H63: -54812.962 | I63: -59629.09 | J63: -67111.173 | K63: -67569.006 | L63: -74722.354
B64: Total Shareholders' Equity | C64: 6524.8089 | D64: -2089.8792 | E64: -2721.519 | F64: -5474.697 | G64: -7314.2985 | H64: -6395.2434 | I64: -4045.9023 | J64: -5625.1112 | K64: -4260.8067 | L64: -3666.8275
B65: Total Equity | C65: 6524.8089 | D65: -2089.8792 | E65: -2721.519 | F65: -5474.697 | G65: -7314.2985 | H65: -6395.2434 | I65: -4045.9023 | J65: -5625.1112 | K65: -4260.8067 | L65: -3666.8275
B66: Total Liabilities & Shareholders' Equity | C66: 34924.698 | D66: 29413.511 | E66: 28150.983 | F66: 28702.445 | G66: 42325.88 | H66: 43011.565 | I66: 47356.93 | J66: 47257.531 | K66: 50827.685 | L66: 53290.196
B67: Per Share
B68: Book Value per Share | C68: 7.19542 | D68: -2.55081 | E68: -3.42717 | F68: -7.13688 | G68: -9.80075 | H68: -8.57961 | I68: -5.42783 | J68: -7.55251 | K68: -5.82635 | L68: -5.127
B69: Tangible Book Value per Share | C69: 4.64095 | D69: -5.254603 | E69: -5.922782 | F69: -9.795642 | G69: -13.791095 | H69: -12.378045 | I69: -9.648225 | J69: -12.288652 | K69: -10.624877 | L69: -10.598312
B70: All figures in millions of Euro except per share items.
